Workbook

Sheet How to use
A1: ARS Literature Review: Scopus screening (S1, S2, S3b)
A2: Prepared 07-10-2026 for Ethan Bastian & Ethan Croes (CS/IST pre-master, ARS, DACS4)
A4: What this file is
A5: Title/abstract screening of all 509 unique records found in Scopus, with a suggested decision and reason for each.
A6: The suggestions were made by an AI assistant (Claude) from titles and abstracts only. You must check them: you are responsible for the final decisions.
A8: How to check the screening
A9: 1. Go to the Screening sheet. Column I shows the AI suggestion, column J the reason code (see Criteria sheet).
A10: 2. If you agree, leave column N (yellow) empty. If you disagree, type your own decision in column N: Include, or an exclusion code such as EC6.
A11: 3. Column O (Final decision) updates automatically, and so do the counts on the PRISMA sheet.
A12: 4. Use the filter arrows in the header row to show e.g. only Section 2.3 or only High priority.
A14: Example: row R013 (LoRa relay for detonating explosives) is suggested as EC7. If you think it belongs in 2.1, type Include in N.
A16: Priority (column M), for included records only
... A28: Note: EC6 and EC7 were added during screening because many records were off-topic or only applications. Add them to the exclusion criteria in your review.

Sheet Search log
A1: # | B1: Date | C1: Database | D1: Purpose | E1: Search string | F1: Filters | G1: Results | H1: Note
A2: S1 | B2: 07-10-2026 | C2: Scopus | D2: Routing in LoRa mesh networks (2.1) | E2: TITLE-ABS-KEY( ("LoRa" OR "Meshtastic" OR "MeshCore") AND (mesh OR "multi-hop" OR multihop) AND (routing OR flooding OR relay*) ) AND PUBYEAR > 2013 AND PUBYEAR < 2027 | F2: None | G2: 219 | H2: Used
A3: S2 | B3: 07-10-2026 | C3: Scopus | D3: Security problems in LoRa mesh / multi-hop (2.1, 2.2) | E3: TITLE-ABS-KEY( ("LoRa" OR "LPWAN" OR "Meshtastic" OR "MeshCore") AND (mesh OR "multi-hop" OR multihop OR routing) AND (security OR confidentiality OR vulnerabilit* OR attack*) ) AND PUBYEAR > 2013 AND PUBYEAR < 2027 | F3: None | G3: 103 | H3: Used
A4: S3 | B4: 07-10-2026 | C4: Scopus | D4: Hardware limits of security on constrained devices (2.3) | E4: TITLE-ABS-KEY( ("LoRa" OR "LPWAN" OR microcontroller* OR "ESP32" OR "nRF52*" OR "RP2040") AND ("lightweight cryptography" OR "lightweight encryption" OR "embedded security" OR "resource-constrained" OR "constrained device*") AND (encryption OR authentication OR "energy consumption" OR memory) ) AND PUBYEAR > 2013 AND PUBYEAR < 2027 | F4: None | G4: 1156 | H4: Too broad: matched machine-learning "LoRA" (Low-Rank Adaptation) and TinyML papers. Refined to S3b; not screened
A5: S3b | B5: 07-10-2026 | C5: Scopus | D5: Hardware limits of security on constrained devices (2.3) | E5: TITLE-ABS-KEY( ("LoRa" OR "LPWAN" OR "ESP32" OR "nRF52*" OR "RP2040" OR "Cortex-M*") AND ("lightweight cryptography" OR "lightweight encryption" OR "embedded security" OR "resource-constrained" OR "constrained device*") AND (encrypt* OR cryptograph* OR cipher* OR authenticat*) ) AND NOT TITLE-ABS-KEY("low-rank") AND PUBYEAR > 2013 AND PUBYEAR < 2027 | F5: None | G5: 212 | H5: Used
A6: IEEE | B6: 07-10-2026 | C6: IEEE Xplore | D6: (planned) | E6: Same as S1, S2, S3b without TITLE-ABS-KEY / PUBYEAR | F6: 2014-2026 | H6: Access refused on 07-10-2026; not run. Scopus already indexes most IEEE papers.

Sheet Criteria
A1: Code | B1: Criterion | C1: Why
A2: IC1 | B2: Published 2014-2026 | C2: LoRa became available around 2014-2015
A3: IC2 | B3: Written in English | C3: Most academic output is in English (ARS3 lecture)
A4: IC3 | B4: Peer-reviewed journal/conference paper or book chapter (grey literature added separately) | C4: Quality of sources
A5: IC4 | B5: (2.1) Describes routing/forwarding in multi-hop or mesh LoRa, or its security weaknesses | C5: Sub-question 1
A6: IC5 | B6: (2.3) Implements, measures or analyses the cost of security mechanisms on LoRa-class microcontrollers | C6: Sub-question 3
A7: IC6 | B7: Full text accessible (open access or via UT library) | C7: Checked at full-text stage
A9: Code | B9: Exclusion reason | C9: Count (live)
A10: EC1 | B10: Single-hop / star LoRaWAN only, no multi-hop element | C10: =COUNTIF(Screening!$O$2:$O$510,A10) -> 5
A11: EC2 | B11: Physical layer only (modulation, coding, interference); no routing or security relevance | C11: =COUNTIF(Screening!$O$2:$O$510,A11) -> 3
A12: EC3 | B12: Hardware far above LoRa-node class (e.g. Linux servers, cloud) | C12: =COUNTIF(Screening!$O$2:$O$510,A12) -> 1
A13: EC4 | B13: Not a full paper (proceedings front matter, poster, demo, short abstract) | C13: =COUNTIF(Screening!$O$2:$O$510,A13) -> 31
A14: EC5 | B14: Duplicate or earlier version of a paper already screened | C14: =COUNTIF(Screening!$O$2:$O$510,A14) -> 3
A15: EC6 | B15: Off-topic: not about LoRa multi-hop routing/security, nor security cost on constrained hardware | C15: =COUNTIF(Screening!$O$2:$O$510,A15) -> 164
A16: EC7 | B16: Application-focused: uses LoRa (mesh) as a tool, no analysis of routing or security mechanisms | C16: =COUNTIF(Screening!$O$2:$O$510,A16) -> 51
A17: EC8 | B17: Not written in English | C17: =COUNTIF(Screening!$O$2:$O$510,A17) -> 3
A19: Category | B19: Meaning | C19: Section
A20: SURVEY | B20: Survey or review of multi-hop / mesh LoRa | C20: 2.1
A21: COMMUNITY | B21: Meshtastic, MeshCore, Pymesh or other community mesh systems | C21: 2.1
A22: PROTO | B22: Routing protocol design or evaluation for LoRa mesh | C22: 2.1
A23: FLOOD | B23: Flooding, gossip, broadcast or concurrent-transmission forwarding | C23: 2.1
A24: RELAY | B24: Relays or LoRaWAN multi-hop extensions (gateway-centred) | C24: 2.1
A25: EVAL | B25: Experimental or simulation evaluation of a LoRa mesh | C25: 2.1
A26: SEC | B26: Security weaknesses or protection in LoRa mesh / multi-hop | C26: 2.1 / 2.2
A27: FOR24 | B27: Secure-routing or trust technique (general, for 2.4) | C27: 2.4
A28: HWSURVEY | B28: Survey of security on constrained devices | C28: 2.3
A29: HWLORA | B29: Security mechanism implemented or measured on LoRa nodes | C29: 2.3
A30: HWBENCH | B30: Symmetric / lightweight crypto benchmarked on microcontrollers | C30: 2.3
A31: HWPKC | B31: Public-key, key exchange or post-quantum cost on microcontrollers | C31: 2.3

Sheet Screening
A1: ID | B1: Found by | C1: Title | D1: Year | E1: Type | F1: Authors | G1: Source | H1: DOI | I1: AI suggestion | J1: Reason code | K1: Section | L1: Category | M1: Priority | N1: Your decision (optional) | O1: Final decision | P1: Abstract
A2: R001 | B2: S1 | C2: 2017 13th Annual Conference on Wireless On-Demand Network Systems and Services, WONS 2017 - Proceedings | D2: 2017 | E2: Conference review | G2: 2017 13th Annual Conference on Wireless On-Demand Network Systems and Services, WONS 2017 - Proceedings | I2: Exclude | J2: EC4 | O2: =IF(N2="",IF(I2="Include","Include",J2),N2) -> EC4 | P2: The proceedings contain 27 papers. The topics discussed include: a dynamic and autonomous channel selection strategy for interference avoidance in 802.11; on the feasibility of collision detection in full-duplex 802.11 radio; TraceMixer: privacy-preserving crowd-sensing sans trusted third party; on the sensitivity of geo-based content sharing to location errors; the more you speak, the less you hear: on dynamic announcement intervals in wireless on-demand networks; promotion of cooperation in public goods game by socialized speed-restricted movement; offloading on the edge: performance and cost analysis of local data storage and offloading in HetNets; active energy management for harvesting enabled wireless sensor network; energy-efficient analog sensing for large scale, high-density persistent wireless monitoring; on the application of LoRa LPWAN technology in sailing monitoring system; an alternative congestion control using an enhanced contention based forwarding for vehicular networks; efficient mmwave wireless backhauling for dense small-cell deployments; dynamic RPL for multi-hop routing in IoT applications; and an SMDP approach to optimal PHY configuration in wireless networks.
A3: R002 | B3: S1 | C3: Increased flexibility in long-range IoT deployments with transparent and light-weight 2-hop LoRa approach | D3: 2019 | E3: Conference paper | F3: Diop, M.; Pham, C. | G3: IFIP Wireless Days | H3: 10.1109/wd.2019.8734228 | I3: Include | K3: 2.1 | L3: RELAY | M3: Medium | O3: =IF(N3="",IF(I3="Include","Include",J3),N3) -> Include | P3: LoRa is a recent low-power and long-range sub-GHz radio technology where devices can communicate in 1-hop to a gateway several kilometers away. Long-range radios typically remove the complexity of maintaining a multi-hop network with intermediate nodes for relaying information. Nonetheless, even with the increased range, 1-hop connectivity can be difficult to achieve in real-world deployment scenario, especially for remote and rural areas where density of gateways is low and where devices/gateway are usually deployed for a specific application. This article describes a 2-hop LoRa approach to seamlessly extend a deployed LoRa network in order to reduce both packet losses and transmission cost. We introduce a smart and battery-operated relay-device that can be added after a deployment campaign to transparently provide an extra hop between the remote devices and the gateway. Field tests are conducted to assess network reliability by dynamic insertion of a relay-device between the remote end-devices and the gateway, without advertising its presence. Energy consumption is also discussed. © 2019 IEEE.
A4: R003 | B4: S1 | C4: Distributed network communication using B.A.T.M.A.N. algorithm over LoRa | D4: 2021 | E4: Conference paper | F4: Chache, F.M.; Maxon, S.; Narayanan, R.M.; Bharadwaj, R. | G4: Proceedings of SPIE - The International Society for Optical Engineering | H4: 10.1117/12.2588317 | I4: Include | K4: 2.1 | L4: PROTO | M4: Medium | O4: =IF(N4="",IF(I4="Include","Include",J4),N4) -> Include | P4: Internet of Things (IoT) has become a fast growing research topic in recent years. Internet connected sensors and devices allow for the collection and processing of a wealth of data. This in conjunction with sensor fusion can provide greater accuracy in object recognition and detection surpassing what could be obtained by sensors operating independently. However these distributed sensors must often operate in environments with poor to no access to the internet which can greatly reduce their effectiveness. Additionally these sensors can be attached to highly dynamic platforms further complicating communication and data routing. One possible solution is to use the B.A.T.M.A.N. (Better Approach To Mobile Ad hoc Networking) routing protocol adapted for use with LoRa, a low power long range RF protocol, to route sensor data through other nodes in order to reach internet access points and allow these devices to interact with the cloud that would have otherwise been unable. Other adaptations to the algorithm will be investigated, such as including other sensors, like GPS and message signal strength to better predict route quality. This system shows promise to be an effective, fault-tolerant solution for this application. © 2021 SPIE.
A5: R004 | B5: S1 | C5: Hybrid LoRa Mesh Routing with Energy based Clustering in Heterogeneous IoT Environment | D5: 2025 | E5: Conference paper | F5: Su, A.; Abbas, F.H.; Kurdi, W.H.M.; Farhoud, H.A.; Khazaal, W.M.; Al Attabi, K. | G5: 2025 International Conference on Next Generation Computing Systems: Intelligent System for Sustainable Development, ICNGCS 2025 - Conference Proceedings | H5: 10.1109/icngcs64900.2025.11183332 | I5: Include | K5: 2.1 | L5: PROTO | M5: Low | O5: =IF(N5="",IF(I5="Include","Include",J5),N5) -> Include | P5: In recent times one of the trending technologies that are used for data collection is Internal of Things (IoT), which is applied in numerous applications of the smart devices. Due to the massive volume of data that this technology controls, smart device data- collecting procedure is quite complex, which increases delay and power consumption throughout the data- gathering process. Mainly to improve the efficiency of the smart devices and to provide effective data transmission through routing, in this article a Hybrid LoRa Mesh Routing with energy-based clustering (HLRECH) is developed. The core modules of the proposed model are the Hybrid LoRa Mesh Routing and Energy Consumption Model and the Energy-based Clustering Model. The implementation of this concept is carried out, and the software NS3 and the parameters that are involved in the analysis of the network model are routing overhead, end-to-end delay, vehicle lifetime, cluster efficiency, and the data delivery ratio. Based on the examination of the results, it is evident that HLRECH outperforms the other approaches in terms of efficiency and cluster longevity. © 2025 IEEE.
A6: R005 | B6: S1 | C6: R-AODV: Reverse Ad-Hoc On-Demand Distance Vector Routing Algorithm With LoRa Mesh Based for Emergency Alert System | D6: 2023 | E6: Conference paper | F6: Thaenthong, J.; Pimsen, T.; Chidchuea, K. | G6: 2023 15th International Conference on Information Technology and Electrical Engineering, ICITEE 2023 | H6: 10.1109/icitee59582.2023.10317648 | I6: Include | K6: 2.1 | L6: PROTO | M6: Medium | O6: =IF(N6="",IF(I6="Include","Include",J6),N6) -> Include | P6: This research introduces a LoRa mesh network for emergency notification systems, which addresses the challenges of the conventional point-to-point LoRa system, such as limited transmission range and lack of backup paths. The mesh network comprises nodes that serve as relays, facilitating multi-hop data transmission to the gateway. The network also adapts to node failures and route changes by employing the Reverse Ad-hoc On-demand Distance Vector (R-AODV) routing algorithm. The performance of the proposed system was assessed through three types of tests: point-to-point, multi-hop, and node failure. The results indicate that the LoRa mesh network improves network coverage and reliability for emergency communication. The average delay for sending alert messages from the gateway neighbor node to the gateway is 0.82s, from the alarm node to the gateway is 1.54s in normal conditions, and 11.65s in case of a gateway neighbor node failure. The user satisfaction score is 4.31 out of 5. © 2023 IEEE.
A7: R006 | B7: S1 | C7: A Multi-Hop Routing Solution for Low Latency and Energy Efficiency in Large-Scale LoRa IoT | D7: 2025 | E7: Journal article | F7: Misbahuddin, M.; Iqbal, M.S.; Akbar, L.A.S.I. | G7: International Journal of Computers, Communications and Control | H7: 10.15837/ijccc.2025.3.6501 | I7: Include | K7: 2.1 | L7: PROTO | M7: Medium | O7: =IF(N7="",IF(I7="Include","Include",J7),N7) -> Include | P7: This paper presents a novel multi-hop routing approach for large-scale LoRa IoT networks that aims to solve the challenges of low latency and energy efficiency. The proposed protocol seeks to minimize energy usage and enable wirelessly data transfer by utilizing the unique features of LoRa communication technology. To ensure reliable communication in a multi-hop context, the protocol includes a dynamic routing mechanism that optimizes network latency and prevents data packet collisions. Furthermore, scalability is another important consideration since it permits the flexible addition of new nodes. The simulation results show that the proposed approach is effective, which shows improved energy savings, less latency, and strong flexibility. These results offer a promising solution for optimizing the performance of large-scale LoRa IoT deployments. © (2025), (Agora University). All rights reserved.
A8: R007 | B8: S1 | C8: QoS Extension to a B.A.T.M.A.N. based LoRa Mesh Network | D8: 2021 | E8: Conference paper | F8: Chache, F.M.; Maxon, S.; Narayanan, R.M.; Bharadwaj, R. | G8: Proceedings - IEEE Military Communications Conference MILCOM | H8: 10.1109/milcom52596.2021.9653022 | I8: Include | K8: 2.1 | L8: PROTO | M8: Low | O8: =IF(N8="",IF(I8="Include","Include",J8),N8) -> Include | P8: To be useful, wireless sensor networks (WSNs) must be relied upon even when dispersed across environments that lack consistent internet access. To this end, we propose a mesh network architecture based on the Better Approach to Mobile Ad-hoc Networking (B.A.T.M.A.N.) algorithm in conjunction with the long range, low power communication protocol, LoRa, to transmit messages. Adaptations including methods of time synchronization, slotted ALOHA transmission and Quality of Service (QoS) considerations with a network-traffic-aware data routing protocol for a multi-source/multi-sink network configuration have been implemented. With this solution, nodes can create an ad-hoc network, sharing internet access and greatly expanding the network coverage without the need for any additional infrastructure. Our QoS-aware routing metrics have been tested in simulation and show performance improvements over traditional B.A.T.M.A.N. destination routing algorithms in these low data rate systems. © 2021 IEEE.
A9: R008 | B9: S1 | C9: Development of a Mathematical Model for Estimating the Energy Efficiency and Throughput of a Decentralized LoRa Network with Account for Dynamically Changing Signal Propagation Conditions | D9: 2026 | E9: Conference paper | F9: Tsoy, D.C.; Kazadaev, L.M.; Lipatkin, V.I.; Ryumshin, K.Y. | G9: 2026 Systems of Signals Generating and Processing in the Field of on Board Communications, SOSG 2026 - Conference Proceedings | H9: 10.1109/ieeeconf68869.2026.11460393 | I9: Include | K9: 2.1 | L9: PROTO | M9: Medium | O9: =IF(N9="",IF(I9="Include","Include",J9),N9) -> Include | P9: This article addresses the problem of evaluating energy efficiency and data throughput in decentralized LoRa mesh networks under dynamically changing propagation conditions. In contrast to centralized LoRaWAN architectures, where devices communicate exclusively through gateways, the mesh topology considered here enables multi-hop data delivery via intermediate nodes. This is especially relevant in conditions of urban dense development, where direct node-to-gateway links are often disrupted by obstacles or excessive distance. A simulation model of the physical layer (PHY) of LoRa is developed in MATLAB, incorporating an AWGN channel and a frequency-selective Rayleigh TDL channel calibrated according to ITU-R P.1411-10 recommendations. The packet error rate (PER) and bit error rate (BER) are used as the primary quality metrics, while network throughput and end-to-end reliability are evaluated as functions of the number of relay hops. The effect of the LoRa coding rate (CR = 4/5 versus CR = 4/8) on the residual error floor and end-to-end performance is investigated as a means of mitigating irreducible fading losses. ©2026 IEEE.
A10: R009 | B10: S1 | C10: A GNN-Based Learning Approach for Energy Optimization in Relay-Assisted IoT Networks | D10: 2025 | E10: Conference paper | F10: Yang, H.; Ji, H.; Huang, Z.; Wu, X. | G10: IEEE Wireless Communications and Networking Conference, WCNC | H10: 10.1109/wcnc61545.2025.10978775 | I10: Include | K10: 2.1 | L10: RELAY | M10: Low | O10: =IF(N10="",IF(I10="Include","Include",J10),N10) -> Include | P10: Minimizing energy consumption is critical for the long-range (LoRa) Internet of Things (IoT) networks, to extend the battery lifetime of end devices (EDs) while reducing the maintenance cost. To overcome the excessive computational complexity required by the traditional optimization methods, learning approaches such as deep neural network (DNN) and reinforcement learning (RL) have been researched in wireless networks, where star topologies are widely employed. In contrast, LoRa usually deploys relays to assist the connection between the EDs and the gateway (GW), leading to a much more complex network topology. Consequently, DNN and RL would become less effective in LoRa, since those methods are difficult to learn the complex network topology constructed by LoRa. In this paper, we propose a learning method based on graph neural network (GNN), which is known for its prominent ability to capture and represent intricate graph-structural dependencies, to tackle the energy optimization problem for relay-assisted LoRa. Specifically, the multi-hop LoRa network is modeled as a directed graph, with channel state information (CSI) defined as node features, while the spreading factor and transmission power are deemed labels. A hierarchical message aggregation mechanism is proposed to effectively capture the multi-hop structural dependencies, followed by the process of inductive learning. Results show that against conventional optimization algorithms, the proposed method can achieve near-optimal energy consumption with a gap of 10% to 16%, while reducing the runtime by about six orders of magnitude. Compared to DNN, the GNN-based model can provide an energy saving of up to 32%, at a similar level of inference time. © 2025 IEEE.
A11: R010 | B11: S1 | C11: A Comparative Evaluation of LoRa Mesh, Peer-to-Peer and Satellite Communication Systems for Lunar IoT Applications | D11: 2026 | E11: Conference paper | F11: Impraim, N.N.; Bayrak, S. | G11: RAST 2026 - 11th International Conference on Recent Advances in Air and Space Technologies, Conference Program | H11: 10.1109/rast69551.2026.11672553 | I11: Include | K11: 2.1 | L11: EVAL | M11: Low | O11: =IF(N11="",IF(I11="Include","Include",J11),N11) -> Include | P11: This paper presents a performance comparison of three LoRa-based communication systems. Mesh Networks, Point-to-Point (P2P), and satellite gateways for Lunar-IoT networks. In this study, an evaluation framework has been developed that reflects the lunar environment. This includes factors like radiation-induced bit errors, extreme temperature changes (+130°C to -170°C), 14-day day/night cycles, terrain-related path loss from craters and regolith, and vacuum propagation. In testing 25 distributed nodes over a 5 km coverage area, the mesh network achieved a packet delivery rate (PDR) of 97.06%. In contrast, the P2P architecture had a PDR of 23.60%, while the satellite system achieved 74.15%. P2P had the lowest latency at (319 ms), and the least energy use, but single-hop limits resulted in 76% of transmissions failing in low-density lunar deployments. Satellite communication ensured reliable connections but came with much higher latency (2079 ms) and energy usage. Networks using multi-hop routing with a 1.5 km distance between nodes created the best balance of reliability and efficiency for lunar operations. This study provides performance comparisons essential for planning a LoRa-based communication system on the Moon. © 2026 IEEE.
A12: R011 | B12: S1 | C12: Analytic Model of a Mesh Topology based on LoRa Technology | D12: 2020 | E12: Conference paper | F12: Kirichek, R.; Vishnevsky, V.; Pham, V.D.; Koucheryavy, A. | G12: International Conference on Advanced Communication Technology, ICACT | H12: 10.23919/icact48636.2020.9061519 | I12: Include | K12: 2.1 | L12: PROTO | M12: Medium | O12: =IF(N12="",IF(I12="Include","Include",J12),N12) -> Include | P12: In the last decade, the Internet of Things (IoT) technologies have brought a lot of applications in different fields. Many communication technologies have been developed in order to connect everything to each other and to the Internet. Besides, the long-range power-efficient wireless technologies have emerged such as LoRa (Long Range), which enables transmission over long distances with low energy consumption and can work within p2p, star or mesh topologies. In this paper, we analyze a model of a mesh topology for the LoRa network, which is attracting more interest in the applications of Smart City and Smart Agriculture. While the mesh topology is described by a graph, a method of route selection is considered based on the link quality related to Received Signal Strength Indication (RSSI) to find the optimal path from a source to a sink node. The network performance is evaluated by considering each node as a queueing system. As the analytic results, the routes are found from device nodes to the gateway, and the delivery latency is analyzed in the dependence on the load intensity and the number of relay nodes. © 2020 Global IT Research Institute - GIRI.
A13: R012 | B13: S1 | C13: Design Considerations and Performance Evaluation of Gossip Routing in LoRa-Based Linear Networks | D13: 2023 | E13: Journal article | F13: Liaqat, R.M.; Branch, P.; But, J. | G13: Future Internet | H13: 10.3390/fi15110366 | I13: Include | K13: 2.1 | L13: FLOOD | M13: High | O13: =IF(N13="",IF(I13="Include","Include",J13),N13) -> Include | P13: Linear networks (sometimes called chain-type networks) occur frequently in Internet of Things (IoT) applications, where sensors or actuators are deployed along pipelines, roads, railways, mines, and international borders. LoRa, short for Long Range, is an increasingly important technology for the IoT with great potential for linear networking. Despite its potential, limited research has explored LoRa’s implementation in such networks. In this paper, we addressed two important issues related to LoRa linear networks. The first is contention, when multiple nodes attempt to access a shared channel. Although originally designed to deal with interference, LoRa’s technique of synchronisation with a transmission node permits a novel approach to contention, which we explored. The second issue revolves around routing, where linear networks permit simpler strategies, in contrast to the common routing complexities of mesh networks. We present gossip routing as a very lightweight approach to routing. All our evaluations were carried out using real equipment by developing real networks. We constructed networks of up to three hops in length and up to three nodes in width. We carried out experiments looking at contention and routing. We demonstrate using the novel approach that we could achieve up to 98% throughput. We compared its performance considering collocated scenarios that achieved 84% and 89% throughputby using relay widths of two and three at each hop, respectively. Lastly, we demonstrate the effectiveness of gossip routing by using various transmission probabilities. We noticed high performance up to 98% throughputat (Formula presented.) = 0.90 and (Formula presented.) = 0.80 by employing two and three active relay nodes, respectively. The experimental result showed that, at (Formula presented.) = 0.40, it achieved an average performance of 62.8% and 73.77% by using two and three active relay nodes, respectively. We concluded that LoRa is an excellent technology for Internet of Things applications where sensors and actuators are deployed in an approximately linear fashion. © 2023 by the authors.
A14: R013 | B14: S1 | C14: A LoRa relay based system for detonating explosives in underground mines | D14: 2020 | E14: Conference paper | F14: Branch, P.; Cricenti, T. | G14: Proceedings of the IEEE International Conference on Industrial Technology | H14: 10.1109/icit45562.2020.9067213 | I14: Exclude | J14: EC7 | O14: =IF(N14="",IF(I14="Include","Include",J14),N14) -> EC7 | P14: In this paper we present our work on the use of LoRa as a network technology for detonation of low explosives in underground mining. Using explosives underground is a potentially hazardous activity that mining companies are keen to make safer by removing personnel from near the site of the detonation. Currently detonation is commonly carried out using lengths of copper cable or infrared transmission, both of which limit the distance between the initiator and the explosives. The wireless technology LoRa, is an attractive alternative. LoRa has a much longer transmission range than infrared transmission and other wireless technologies such as WiFi and ZigBee. We have developed and trialed in a working underground mine a prototype system for carrying out such detonations. The system makes use of LoRa as a multi-hop message passing system from an Initiator to a Detonator via a number of Relays. We describe the messages that are passed through the network. We also describe how we deal with contention, broadcast storms and duplicate messages. Our approach is robust, easy to deploy and gives deterministic delay. We also present measurements of signal strength taken underground. Our results indicate that underground LoRa wireless transmission suffers severe fading without line of sight but where this is a line of sight underground, we show that LoRa propagates considerable distances. © 2020 IEEE.
A15: R014 | B15: S1, S2 | C15: MSWiM 2021 - Proceedings of the 24th International ACM Conference on Modeling, Analysis and Simulation of Wireless and Mobile Systems | D15: 2021 | E15: Conference review | G15: MSWiM 2021 - Proceedings of the 24th International ACM Conference on Modeling, Analysis and Simulation of Wireless and Mobile Systems | I15: Exclude | J15: EC4 | O15: =IF(N15="",IF(I15="Include","Include",J15),N15) -> EC4 | P15: The proceedings contain 29 papers. The topics discussed include: preventing failures of cooperative maneuvers among connected and automated vehicles; global energy optimization strategy based on delay constraints in edge computing environment; profit maximization for service placement and request assignment in edge computing via deep reinforcement learning; accelerating the simulation of wireless communication protocols using asynchronous parallelism; modeling and simulation of reconfigurable intelligent surfaces for hybrid aerial and ground-based vehicular communications; an energy-efficient smart space system using lora network with deadline and security constraints; a novel harvesting-aware RL-based opportunistic routing protocol for underwater sensor networks; and simple and efficient collision-free channel access in multi-hop wireless networks.
A16: R015 | B16: S1 | C16: Energy-Efficient Multi-Hop LoRa Communication in Forested Environments via Proximal Policy Optimization | D16: 2026 | E16: Journal article | F16: Jumali, M.K.B.; Guan, L.K.; Moung, E.G.; Angeline, L.; Wang, T.; Kin, K.T.T. | G16: International Journal of Advanced Computer Science and Applications | H16: 10.14569/ijacsa.2026.0170436 | I16: Include | K16: 2.1 | L16: PROTO | M16: Low | O16: =IF(N16="",IF(I16="Include","Include",J16),N16) -> Include | P16: Multi-hop LoRa networks extend coverage for large-scale Internet of Things deployments but are severely limited by interference-induced collisions, retransmissions, and rapid battery depletion of relay nodes. Conventional routing strategies that minimize hop count or rely on static heuristics fail to account for dynamic medium contention and its impact on energy consumption and reliability. This paper proposes a Proximal Policy Optimization (PPO)-based routing framework for multi-hop LoRa networks that learns interference-aware and energy-efficient routing policies through reinforcement learning. A discrete-event simulation framework is developed to model LoRa physical-layer behaviour, co-spreading-factor interference, adaptive data rate control, and battery-limited relay nodes under multi-source traffic. The routing problem is formulated as a Markov Decision Process (MDP) in which the PPO agent selects next-hop relays based on local topology, relay load, and channel occupancy, while physical-layer parameters are adapted independently using a standards-inspired physical-layer parameters are adapted independently using a standards-inspired ADR mechanism (ADR) mechanism. Simulation results show that the proposed approach achieves a packet delivery ratio of up to 73.7%, reduces collision rates by approximately 46% compared with Random routing, and lowers the average energy consumption per delivered packet to about 206 mJ, outperforming Shortest Path and Ad hoc On-Demand Distance Vector (AODV)-like routing. These gains are achieved by learning spatially diverse routing paths that mitigate relay congestion and reduce collision-induced retransmissions. © 2026, The Author(s).
A17: R016 | B17: S1 | C17: Simulated Disaster Warning System for Remote Areas using Multi-Hop LEACH over LoRa Mesh Network | D17: 2026 | E17: Conference paper | F17: Pradeep Kumar, G.; Afeef Ahmed Kamal, A.; Bala Ramanan, B.; Imthiyaz Ahamed, A.; Siddharth, M. | G17: 4th International Conference on Integrated Circuits and Communication Systems, ICICACS 2026 | H17: 10.1109/icicacs68679.2026.11578885 | I17: Include | K17: 2.1 | L17: PROTO | M17: Low | O17: =IF(N17="",IF(I17="Include","Include",J17),N17) -> Include | P17: This research addresses the critical failure of conventional communication infrastructures during climatic disasters, particularly in geographically isolated regions where "last mile"connectivity is often the first to fail. Conventional systems like GSM and standard LoRaWAN suffer from single points of failure and congestion. To overcome these limitations, we propose a robust, autonomously survivable architecture synthesizing Multi-Hop Low energy Adaptive Clustering Hierarchy (LEACH) protocols with the Long Range (LoRa) physical layer. The proposed method introduces a decentralized mesh topology controlled by a novel "Node Rank"(NR) algorithmic fitness function, which deterministically assigns Cluster Heads based on residual energy, proximity to the sink, and connectivity degree. Extensive stochastic modeling and discrete-event simulations in Network Simulator 2 (NS2) demonstrate that this approach achieves a 96% Packet Delivery Ratio (PDR), reduces end-to-end latency to 1.9s, and extends network lifetime by 80% compared to AODV and single-hop paradigms. These results confirm the system's viability as a resilient backbone for next-generation disaster informatics, ensuring reliable early warnings even when traditional networks collapse. © 2026 IEEE.
A18: R017 | B18: S1 | C18: Cross-network cross-interface relaying via LoRa-ZigBee synergy: Enabling energy-efficient delay-constrained communication across low-power IoT networks | D18: 2026 | E18: Journal article | F18: Qin, H.; Li, N.; Yang, G.; Peng, Y. | G18: Internet of Things (The Netherlands) | H18: 10.1016/j.iot.2026.101878 | I18: Exclude | J18: EC6 | O18: =IF(N18="",IF(I18="Include","Include",J18),N18) -> EC6 | P18: The rapid expansion of the Internet of Things (IoT) ecosystem has propelled widespread deployment of distributed low-power wireless networks, among which ZigBee stands out for diverse innovative applications. However, energy-efficient cross-network communication remains challenging, as existing solutions like multi-hop ZigBee and one-hop LoRa entail trade-offs between communication delays and deployment costs. To tackle these issues, we propose a novel cross-interface relaying paradigm that utilizes a star topology within each ZigBee network and designates a relay node with an additional LoRa interface to bridge networks via a central LoRa gateway. Compared with existing methods, this approach reduces energy consumption and costs while improving scalability. To implement this paradigm while balancing energy conservation with delay guarantees, we introduce a Cross-network Cross-interface Relaying (CCR) scheme, which jointly schedules LoRa and ZigBee transmission behaviors to minimize energy consumption under delay constraints. CCR uses a scheduling framework that breaks down end-to-end delay constraints into link-level constraints, enabling global optimization of transmission parameters and dynamic adaptation to link quality variations. The effectiveness of CCR is demonstrated through extensive field tests on a prototype implemented on Raspberry Pi 3B+. Results show that CCR reduces energy consumption by 55.4% and 39.1% compared with an advanced LoRa communication protocol and a state-of-the-art cross-interface relaying scheme, respectively, while ensuring that 98.7% of packets satisfy their delay constraints. These findings highlight the potential of CCR for efficient and reliable cross-network communication in large-scale IoT deployments. © 2026 Elsevier B.V.
A19: R018 | B19: S1 | C19: Large and reliable data transfer service for LoRa mesh network applications | D19: 2026 | E19: Journal article | F19: Miquel Solé, J.; Pueyo Centelles, R.; Freitag, F.; Meseguer, R.; Baig Viñas, R. | G19: Computer Communications | H19: 10.1016/j.comcom.2025.108404 | I19: Include | K19: 2.1 | L19: PROTO | M19: Medium | O19: =IF(N19="",IF(I19="Include","Include",J19),N19) -> Include | P19: Recently, LoRa mesh networks have appeared as a communication technology for Internet of Things (IoT) devices. Through node-to-node communication, novel distributed IoT applications that extend beyond the capabilities of the LoRaWAN architecture can be enabled. However, current technologies for LoRa networks do not provide mechanisms for large and reliable data transfers between IoT nodes. This paper presents a service for such data transfers in LoRa mesh network applications, along with the protocol and formats used for inter-node communication. We explain the design choices and detail the implementation decisions to ensure that this service is practically usable. To this end, the service was integrated into the LoRaMesher library and is available as an open-source operational implementation. In experiments with ten real nodes and two network topologies, we observe that the service effectively achieves a large and reliable message delivery in an environment of concurrent transmissions and packet losses. In contrast, the cost of reliability for large data transfers is an increased number of messages and a higher delivery time. With the integration of the service into the LoRaMesher technology, developers now have a library that provides a reliable and large payload service for LoRa mesh network applications, eliminating the need to develop such capacity as a specific application-level solution. © 2025
A20: R019 | B20: S1 | C20: Experimental LoRa Network Power Consumption Model Using Multi-Hops | D20: 2022 | E20: Conference paper | F20: Alexander, U.; Bolshakov, I.; Voskov, L.; Rolich, A. | G20: Moscow Workshop on Electronic and Networking Technologies, MWENT 2022 - Proceedings | H20: 10.1109/mwent55238.2022.9802378 | I20: Include | K20: 2.1 | L20: RELAY | M20: Low | O20: =IF(N20="",IF(I20="Include","Include",J20),N20) -> Include | P20: The article describes the study of data transmission methods in heterogeneous networks using LoRa relay and NB-IoT gateway for use in an underdeveloped or absent Internet network infrastructure. The analysis of the subject area is carried out, a multistage architecture of a heterogeneous network of the Internet of Things is proposed, using repeaters and a gateway to collect remote data. A method and a calculation model of energy consumption for the transmission of collected data using repeaters is proposed, which makes it possible to increase the energy efficiency of data transmission from end devices using autonomous powersources. A prototype of a data acquisition system withretransmission has been developed, which confirms the theoretical calculations. The practical value lies in increasing thebattery life and expanding the network coverage area. © 2022 IEEE.
A21: R020 | B21: S1 | C21: Reducing Routing Overhead with a Clustering Protocol Based on Ad hoc Distance Vector and Dynamic Source Routing Protocols | D21: 2022 | E21: Conference paper | F21: Kebeng, T.O.; Sheikh, S.M.; Kgwadi, M. | G21: 5th International Conference on Artificial Intelligence, Big Data, Computing and Data Communication Systems, icABCD 2022 - Proceedings | H21: 10.1109/icabcd54961.2022.9856116 | I21: Include | K21: 2.1 | L21: PROTO | M21: Low | O21: =IF(N21="",IF(I21="Include","Include",J21),N21) -> Include | P21: Some wireless network applications only need to send data infrequently and at low bit rates. To save costs, these networks use modest devices with limited resources (bandwidth, power) or legacy technology. Technologies such as Bluetooth Low Energy, Lora Wide Area Networks (LoRAWAN), Zigbee, legacy WIFI among others, are suited for such applications. Since bandwidth is a limited resource for such networks, route discovery needs to use as little as possible, leaving most of the bandwidth available for data transfer. In this paper, the routing protocol for use in wireless, multihop ad-hoc networks, the Ad-Hoc Distance Vector (AODV) routing protocol is compared to a novel routing protocol called Cluster Based AODV (CLUBAA). The comparison is made using simulations, and the results show CLUBAA to have better bandwidth utilization due to its low Normalized Routing Overhead (NRO) for infrequent route discovery requests. The results further expand on the region of the curve where CLUBAA outperformed AODV, showing that there is a niche area where CLUBAA could be a good bandwidth saving alternative to AODV. © 2022 IEEE.
A22: R021 | B22: S1 | C22: 23rd International Conference on Distributed Computer and Communication Networks, DCCN 2020 | D22: 2020 | E22: Journal article | G22: Lecture Notes in Computer Science (including subseries Lecture Notes in Artificial Intelligence and Lecture Notes in Bioinformatics) | I22: Exclude | J22: EC4 | O22: =IF(N22="",IF(I22="Include","Include",J22),N22) -> EC4 | P22: The proceedings contain 55 papers. The special focus in this conference is on Distributed Computer and Communication Networks. The topics include: Architectural ML Framework for IoT Services Delivery Based on Microservices; applying Machine Learning to Data from a Structured Database in a Research Institute to Support Decision Making; generation of Metadata for Network Control; IoT Traffic Prediction with Neural Networks Learning Based on SDN Infrastructure; Transmission Latency Analysis in Cloud-RAN; Resource Queuing System with Preemptive Priority for Performance Analysis of 5G NR Systems; redundant Servicing of a Flow of Heterogeneous Requests Critical to the Total Waiting Time During the Multi-path Passage of a Sequence of Info-Communication Nodes; preface; Power Domain NOMA Without SIC in Downlink CSS-Based LoRa Networks; agriculture Management Based on LoRa Edge Computing System; dynamic Algorithm for Building Future Networks Based on Intelligent Core Network; Methods and Models for Using Heterogeneous Gateways in the Mesh LPWANs; Research on Using the AODV Protocol for a LoRa Mesh Network; on the Algebraic Theory of Loop Free Routing; queueing System with Two Unreliable Servers and Backup Server as a Model of Hybrid Communication System; flexible Random Early Detection Algorithm for Queue Management in Routers; architecture and Functionality of the Collective Operations Subnet of the Angara Interconnect; The Model of WBAN Data Acquisition Network Based on UFP; Development and Investigation of Model Network IMT2020 with the Use of MEC and Voice Assistant Technologies; Simulation-Based Analysis of Mobility Models for Wireless UAV-to-X Networks; queues with Markovian Arrivals, Phase Type Services, Breakdowns, and Repairs.
A23: R022 | B23: S1 | C23: IEEE Region 10 Annual International Conference, Proceedings/TENCON | D23: 2018 | E23: Conference review | G23: IEEE Region 10 Annual International Conference, Proceedings/TENCON | I23: Exclude | J23: EC4 | O23: =IF(N23="",IF(I23="Include","Include",J23),N23) -> EC4 | P23: The proceedings contain 489 papers. The topics discussed include: design of IoT monitoring system based on LoRa technology for starfruit plantation; automatic optic disc localization using particle swarm optimization technique; performance evaluation of Gbps X-band satellite downlink with transmitter imperfections; describing methods for high-level synthesis of histogram generation and their evaluation; a novel fault-tolerant routing technique for mesh-of-tree based network-on-chip design; gyroscopic stabilizer for 3D mapping device on unmanned ground vehicle; feeder wise net metering service planning using load power demand profile and raw customer billing data; non-uniform quantization based reporting in cooperative cognitive radio; pixel-level crack detection using U-Net; and interference limit based resource allocation for low density signature OFDM in underlay cognitive radio networks.
A24: R023 | B24: S1 | C24: The MauMe network - A LoRa multi-hop collaborative protocol and low-cost implementation example | D24: 2023 | E24: Journal article | F24: Mari, J.-M.; Gabillon, A. | G24: Computer Standards and Interfaces | H24: 10.1016/j.csi.2023.103733 | I24: Include | K24: 2.1 | L24: PROTO | M24: Medium | O24: =IF(N24="",IF(I24="Include","Include",J24),N24) -> Include | P24: Low-cost low-power long-distance LoRa radio devices recently made available on the market allow the emerging of a new generation of networking paradigms on the Internet of Things. While the LoRaWan offers an efficient way of connecting LoRa end-point devices to the internet, LoRaWan nodes do not act as peers, but rather as terminals connected to gateways. As such, the current state of the art does not offer a public protocol for easily taking advantage of the fact that individuals and professionals wishing to aggregate data using LoRa devices are likely to run each a “base-node” on a continuous basis. Such permanently-powered base-nodes could potentially offer an increased cumulated area coverage to other nodes if they would behave as relays. In the present study, an Epidemic Delay Tolerant Network messaging protocol is proposed, which allows multi-hops between peer LoRa relay-nodes through a raw-LoRa controlled-flooding approach. This protocol has been implemented on low-cost LoRa-chip-equipped microcontrollers in the form of an open-source library acting as a network transport-layer. The design analysis concluded that MauMe is better suited for networks with reduced connectivity (≤ 9), and that a 4-connectivity redundant network could allow each user to send several tens of messages several tens of hops away. The proposed approach was tested on three different LoRa network topologies, and the totality of the packets and acknowledgments reached their destination. Furthermore, the network's activity ceased after delivery, confirming the ability of the protocol to return the network to rest after the flooding. The proposed library also offers to users a free emergency-messaging system implemented as an http server embedded in each node and accessible via Wi-fi. End-users can readily use our solution to easily deploy a network of sensors at a much lower cost than when using multiple gateways. The MauMe protocol is a first step towards the creation of collaborative and application-friendly extended-range LoRa-peers networks, and is intended for use in remote regions with scattered housings such as in the islands and atolls of Polynesia. © 2023 Elsevier B.V.
A25: R024 | B25: S1 | C25: Research on Using the AODV Protocol for a LoRa Mesh Network | D25: 2020 | E25: Conference paper | F25: Pham, V.D.; Le, D.T.; Kirichek, R.; Shestakov, A. | G25: Lecture Notes in Computer Science (including subseries Lecture Notes in Artificial Intelligence and Lecture Notes in Bioinformatics) | H25: 10.1007/978-3-030-66471-8_13 | I25: Include | K25: 2.1 | L25: PROTO | M25: Medium | O25: =IF(N25="",IF(I25="Include","Include",J25),N25) -> Include | P25: In this paper, we consider the LoRa technology to expand sensor network coverage in smart sustainable cities. A model of a LoRa mesh network is proposed using the AODV protocol in packet routing. With a simulation model developed based on OMNET++, a series of computer experiments was carried out with changing various parameters. In the experiments results, the end-to-end delay and packet loss ratio were analyzed in the dependence on the number of nodes and packet size in the network. The simulation results show that the latency is relatively high in the LoRa mesh network, but it might be accepted for some applications. © 2020, Springer Nature Switzerland AG.
A26: R025 | B26: S1 | C26: Simple Protocol Design of Multi-Hop Network in Lora | D26: 2019 | E26: Conference paper | F26: Azhari, R.Y.; Firmansyah, E.; Bejo, A. | G26: 2019 2nd International Seminar on Research of Information Technology and Intelligent Systems, ISRITI 2019 | H26: 10.1109/isriti48646.2019.9034662 | I26: Include | K26: 2.1 | L26: PROTO | M26: Low | O26: =IF(N26="",IF(I26="Include","Include",J26),N26) -> Include | P26: Long Range (LORA) is a device capable of communicating remotely with LPWAN topologies. LPWAN cannot do multi-hop so this research needed to be done. There are several multi-hop supporting algorithms such as Media Access Control (MAC) and routing table. This paper discusses a simple routing table algorithm and messages delivered with the requirement that the next node is bigger or smaller than what is sent. Node tables and proposed method in single multi-hop produced 99% PDR. © 2019 IEEE.
A27: R026 | B27: S1, S2 | C27: Exploring open source and proprietary LoRa mesh technologies | D27: 2024 | E27: Journal article | F27: Hammouti, M.; Moussaoui, O.; Hassine, M.; Betari, A. | G27: Indonesian Journal of Electrical Engineering and Computer Science | H27: 10.11591/ijeecs.v34.i2.pp960-969 | I27: Include | K27: 2.1 | L27: SURVEY | M27: High | O27: =IF(N27="",IF(I27="Include","Include",J27),N27) -> Include | P27: This paper explores low power wide area network (LPWAN) LoRa and its diverse variants, encompassing open-source and proprietary wireless mesh networks, operating over the physical LoRa or LoRaWAN layer. The primary challenge lies in defining an optimal LoRa mesh solution that balances cost-effectiveness, energy efficiency, low latency, long-range capability, and security. This study also comprehensively examines key LoRa mesh solutions from 2017 to 2024, as proposed by various authors. Furthermore, a detailed analysis is conducted to contrast open-source and commercial solutions, considering their applications, limitations, issues, characteristics, and pros and cons of mesh routing protocols. In the current landscape, the proliferation of open-source and proprietary LoRa mesh solutions has been instrumental in facilitating the connectivity of internet of things (IoT) devices. However, these solutions pose challenges related to energy consumption, latency, and suboptimal transmission throughput. These challenges are influenced by various LoRa characteristics such as spectrum factor, bandwidth, and transmission power, which directly impact the transmission range. Our research aims to perform a comparative analysis of existing LoRa mesh solutions by, systematically studying their advantages and disadvantages. This analysis offers valuable insights for making informed choices among these solutions in diverse domains for IoT applications. © 2024 Institute of Advanced Engineering and Science. All rights reserved.
A28: R027 | B28: S1 | C28: Multi-Protocol Wireless Mesh Sensor Network | D28: 2024 | E28: Conference paper | F28: Wei, W.J.; Sheng Jovian, L.H.; Choon How, B.L.; Richie, W.R.; Yuan, P.X.; Abhishek, N.V.; Bin Abbas, M.F. | G28: 2024 IEEE VTS Asia Pacific Wireless Communications Symposium, APWCS 2024 | H28: 10.1109/apwcs61586.2024.10679304 | I28: Include | K28: 2.1 | L28: EVAL | M28: Low | O28: =IF(N28="",IF(I28="Include","Include",J28),N28) -> Include | P28: Wireless Sensor Networks (WSNs) are pivotal for real-time environmental monitoring applications. This paper delves into the detailed architecture and performance analysis of two prominent protocols, ESP-NOW and LoRa, within the context of a WSN setup. The ESP-NOW protocol, utilizing a Dynamic Source Routing (DSR) mesh algorithm, excels in throughput, latency, and bandwidth compared to LoRa, making it suitable for high-speed, low-latency communication needs. Conversely, LoRa demonstrates advantages in long-range communication and obstacle penetration. Additionally, the analysis delves into power consumption, where ESP-NOW outshines LoRa in both idle and active network states. This results demonstrated that the energy efficiency of ESP-NOW is particularly advantageous for battery-operated devices and remote deployments. The findings presented also provided valuable insights for optimizing protocol selection and power management strategies in WSN deployments, ensuring efficient and reliable data transmission in diverse environmental monitoring scenarios. © 2024 IEEE.
A29: R028 | B29: S1, S2 | C29: LDPC Over Multihop LoRa Nodes with Peeling Decoder | D29: 2023 | E29: Conference paper | F29: Arifianto, M.S. | G29: Proceeding of 2023 9th International Conference on Wireless and Telematics, ICWT 2023 | H29: 10.1109/icwt58823.2023.10335410 | I29: Exclude | J29: EC2 | O29: =IF(N29="",IF(I29="Include","Include",J29),N29) -> EC2 | P29: Wireless radio communication is expected to reach long distances and be of good quality. To achieve long-distance radio communication, relay stations can be added between the source to the destination points as needed. The utilization of wireless radio introduces vulnerabilities to the quality of communication due to noise and interference. In this research a multihop communications is created using four stationary LoRa nodes. Error correction and detection were added to the multihop communication. The Low-Density Parity Check (LDPC) regular binary 16x32 technique is used in this research for multihop communication at encoder node 1 and decoder node 4. Meanwhile, node 2 and node 3 serve as repeaters between node 1 and node 4. The type of LDPC used is binary encoder, and the decoder uses the peeling technique. Each node's implementation involves the use of hardware modules BeagleBone Black Industrial and LoRa Ebyte. The software utilized includes the debian console and Python programming. This multihop communication has undergone testing for parameters such as processing time, RSSI field test, and peeling error detection and correction ability. © 2023 IEEE.
A30: R029 | B30: S1 | C30: Cost Effective Routing in Large-scale Multi-hop LoRa Networks | D30: 2022 | E30: Conference paper | F30: Feng, S.; Chen, J.; Zhao, Z. | G30: INFOCOM WKSHPS 2022 - IEEE Conference on Computer Communications Workshops | H30: 10.1109/infocomwkshps54753.2022.9798302 | I30: Include | K30: 2.1 | L30: PROTO | M30: Medium | O30: =IF(N30="",IF(I30="Include","Include",J30),N30) -> Include | P30: Low-Power Wide-Area Network (LPWAN) technologies promoted the communication capacities of Internet of Things (IoT) to several or even dozens of kilometers. LoRa is one of these technologies characterized with longrange, low data rates and low power consumption. The LoRaWAN architecture is applied to a star-of-stars topology. However, in several non-line-of-sight or larger scale deployment scenarios, such as underground deployment and large-scale military launch, the single-hop topology may not meet the requirements. Adding gateways to increase coverage may increase deployment complexity and reduce information sharing. Furthermore, the exhaustion of a single node in the network will bring extra cost of replacing the battery, further reducing the network lifetime. Consequently, this paper introduces a multi-hop protocol MLoRa to solve these problems. MLoRa gives a routing strategy upon network layer, which not only brings cost-effective coverage but also lower and balanced energy consumption for the same coverage in LoRa networks. © 2022 IEEE.
A31: R030 | B31: S1, S2 | C31: 17th International Conference on Ad Hoc Networks and Wireless, ADHOC-NOW 2018 | D31: 2018 | E31: Journal article | G31: Lecture Notes in Computer Science (including subseries Lecture Notes in Artificial Intelligence and Lecture Notes in Bioinformatics) | I31: Exclude | J31: EC4 | O31: =IF(N31="",IF(I31="Include","Include",J31),N31) -> EC4 | P31: The proceedings contain 29 papers. The special focus in this conference is on Ad Hoc Networks and Wireless. The topics include: Demo: Do not trust your neighbors! a small iot platform illustrating a man-in-the-middle attack; a fuzzy based energy aware unequal clustering for wireless sensor networks; The trade-offs of cell over-provisioning in IEEE 802.15.4 TSCH networks; wireless network for in-car communication; Enhanced dynamic duty cycle in LoRaWAN network; Specificities of the LoRa™ physical layer for the development of new ad hoc MAC layers; A comparative evaluation of the performance of the multi-hop IoB-DTN routing protocol; Performance of selection combining macro diversity with outage probability constraint in LPWAN; Authenticated preambles for denial of service mitigation in LPWANs; Multi-path selection in RPL based on replication and elimination; communication architecture for unmanned aerial vehicle system; DACAR: Distributed & adaptable crosslayer anticollision and routing protocol for RFID; low frequency mobile communications in underwater networks; FPMIPV6-S: An enhanced mobility protocol for 6LoWPAN-based wireless mobile sensor networks; collaborative state estimation and actuator scheduling for cyber-physical systems under random multiple events; game-based data muling as a service in infrastructureless area; distributed computations in wireless sensor networks by local interactions; SPHERE deployment manager: A tool for deploying IoT sensor networks at large scale; constructing customized multi-hop topologies in dense wireless network testbeds; f-Interop platform and tools: Validating IoT implementations faster; performance evaluation of a rpl hybrid objective function for the smart grid network; latency and lifetime optimization for k-anycast routing algorithm in wireless sensor networks.
A32: R031 | B32: S1, S2 | C32: Secure Energy Constrained LoRa Mesh Network | D32: 2020 | E32: Conference paper | F32: Heeger, D.; Garigan, M.; Tsiropoulou, E.E.; Plusquellic, J. | G32: Lecture Notes in Computer Science (including subseries Lecture Notes in Artificial Intelligence and Lecture Notes in Bioinformatics) | H32: 10.1007/978-3-030-61746-2_17 | I32: Include | K32: 2.1 / 2.2 | L32: SEC | M32: High | O32: =IF(N32="",IF(I32="Include","Include",J32),N32) -> Include | P32: LoRa (Long Range) is a low-power wide-area network technology well-suited for Internet of Things (IoT) applications. In this paper, LoRa is used in a cattle monitoring application where an ad-hoc mesh network is configured to collect GPS and accelerometer data from cattle-worn sensors and relay the collected data to a base station. Free-range cattle monitoring is a challenging application since the battery-powered sensors must be small and energy efficient, and enable data communications over long distances from unpredictable locations. We propose novel changes to the existing LoRa mesh network protocols that minimize energy consumption by using global time synchronization enabled by GPS sensors and a concurrent transmission property unique to LoRa. The mesh routing phase efficiently occurs during every data collection period, making this approach ideal for networking highly mobile sensors. We integrate efficient authentication and encryption techniques in the data exchange operations to prevent spoofing and to provide confidentiality in the message exchanges between the sensors and the base station. The performance of the proposed secure implementation is compared to an equivalent insecure implementation. Multiple cattle distribution scenarios are constructed and compared to evaluate the energy consumption of the proposed scheme. © 2020, Springer Nature Switzerland AG.
A33: R032 | B33: S1 | C33: Hybrid LoRa-Visible-Light Mesh for Ultra-Low-Latency Rural IoT Backhaul | D33: 2026 | E33: Conference paper | F33: Basha, S.M.; Agoramoorthy, M.; Sathiyamoorthy, M.; Prabu, M.; Jeyakumar, D.J. | G33: 2026 8th International Conference on Inventive Material Science and Applications, ICIMA 2026 | H33: 10.1109/icima68728.2026.11564606 | I33: Exclude | J33: EC6 | O33: =IF(N33="",IF(I33="Include","Include",J33),N33) -> EC6 | P33: The need to offer reliable low-cost backhaul connectivity in rural areas is a decisive issue to large scale Internet of Things (IoT) implementations, where standard wireless network solutions are characterized by high latency, subpar coverage, and limited scalability. This is a work that proposes a Hybrid LoRa-Visible-Light Communication (VLC) Mesh architecture that intends on providing IoT backhaul with ultra-low-latency and low-energy usage and low-cost backhaul in underserved regions. The aim of the suggested design is to integrate long-range, low-power robustness of LoRa with high-speed, short-range of VLC in a mesh topology, hence providing strong coverage and high throughput data transmission. The originality of the given approach is that it combines LoRa and VLC technologies seamlessly into a cooperative mesh structure, which allows multi-hop adaptive routing with the minimal transmission delays and maximized energy use. According to experimental assessments and simulations, the backhaul solutions with multiple technologies show a significant reduction in latency, throughput performance, and energy efficiency over the traditional single-technology solutions. This hybrid system presents a sustainable and scalable way of achieving the realization of smart villages, accuracy agriculture, and disaster-resilient IoT systems in rural areas. © 2026 IEEE.
A34: R033 | B34: S1 | C34: Research and Development of Lora-Modulated Signal Retransmission System | D34: 2025 | E34: Conference paper | F34: Tsoi, A.E.; Sattarova, A.I.; Vasiliev, V.Y.; Kazadaev, L.M. | G34: 2025 Systems of Signal Synchronization, Generating and Processing in Telecommunications, SYNCHROINFO 2025 - Conference Proceedings | H34: 10.1109/synchroinfo65403.2025.11079364 | I34: Include | K34: 2.1 | L34: RELAY | M34: Low | O34: =IF(N34="",IF(I34="Include","Include",J34),N34) -> Include | P34: This article focuses on an issue within the LPWAN wireless technology based on LoRa, which often faces challenges in maintaining stable data transmission due to unstable communication conditions between nodes and gateways, and a simulation of node connections and the influence of noise levels to connection stability is presented. In traditional LoRaWAN networks, where devices connect directly to gateways, signal quality deteriorates as distance increases or interference occurs. This leads to data loss and reduced communication reliability. One way to solve this problem is by transitioning to mesh networks, where devices can transmit data not only directly, but also through neighboring nodes. This approach allows for flexible adaptation to network changes and restoration of interrupted connections. However, the correct operation of this technology largely depends on the chosen routing algorithm and whether real-world signal transmission conditions are taken into account. © 2025 IEEE.
A35: R034 | B35: S1 | C35: Make or Break? How LoRaWAN Duty Cycle Impacts Performance in Multihop Networks | D35: 2024 | E35: Journal article | F35: Cotrim, J.R.; Margi, C.B. | G35: IEEE Access | H35: 10.1109/access.2024.3494038 | I35: Include | K35: 2.1 | L35: RELAY | M35: High | O35: =IF(N35="",IF(I35="Include","Include",J35),N35) -> Include | P35: LoRaWAN is a widely adopted protocol for Internet of Things applications with energy constraints and large coverage area demands. The protocol standardization defines a star-of-stars topology, where end-devices send their packets directly to a gateway that forwards the messages to the network server, where they are handled depending on the application. LoRaWAN is at the top of the Long Range (LoRa) physical layer based on the Chirp Spread Spectrum (CSS) modulation, where signals are spread along the frequency by the Spreading Factor (SF). The modulation technique gives the LoRaWAN long range coverage characteristics, that could reach 45 kilometers in theory. Furthermore, the protocol adopts the Industrial, Medical, and Scientific (ISM) frequency band plans, which impose spectrum occupation limitations, and the constraints are defined by a device Duty Cycle (DC). The DC imposes a restriction of 0.1% up to 10% in transmission time, limiting the total amount of messages an end-deceive could send. In order to increase even more the coverage area, many works proposed the adoption of multihop techniques in LoRaWAN networks. Proposed solutions are based on routing and relay approaches, both with benefits and limitations. However, the literature does not explore the DC constraints on the multihop LoRaWAN solutions since packets might be enqueued. The packet delay increases due to the time spent in the buffer, and the delivery ratio decreases because packets are dropped when the buffer is full. To understand such impact, we provide a model to generalize the DC behavior on multihop LoRaWAN networks, focused on the packet delivery ratio and delay metrics. We evaluate our model analytically and experimentally. First, we conducted a numerical comparison between the standard network with the multihop Long Range Wide Area Network (LoRaWAN) over duty cycle constraints. The comparison considers a rural area and the coverage area limited by the 802.11 ah propagation model. The results elucidated the tradeoff between packet size, number of packets, and delay. The two-hop solution could decrease the delay compared with direct transmission using high spreading factors. However, in dense networks, the intermediate device buffer increases the packet delivery delay. It could reduce the packet delivery ratio because the device must respect the duty cycle to forward packets. On the other hand, higher spreading factors decrease the payload size and need more packets to transmit the same message. Then, we compared analytical and experimental results in four relayed scenarios with different numbers of devices and different intermediate device buffer sizes. The results show the DC significantly increases the network delay and packet losses. The intermediate device also causes packet prioritization, making the network unfair. The multihop strategies are relevant for many applications, including coverage area extension, but the solutions must consider the DC constraints as a limitation to their adoption. © 2013 IEEE.
A36: R035 | B36: S1 | C36: Low-power mesh networks for off-grid communication systems: a 5G-fibre hybrid integration solution | D36: 2026 | E36: Journal article | F36: Fan, L.; Li, Y.; Fang, Y.; Wu, X.; Feng, J.; Chen, Y. | G36: International Journal of Information and Communication Technology | H36: 10.1504/ijict.2026.152287 | I36: Exclude | J36: EC7 | O36: =IF(N36="",IF(I36="Include","Include",J36),N36) -> EC7 | P36: This paper proposes a hybrid communication system integrating low-power wireless mesh networks (LP-WMN), 5G backhaul links, and fibre optic communication to enhance the communication capabilities of remote power infrastructure. The system design includes a LoRa-mesh-based perception layer, a 5G millimetre-wave backhaul layer, and fibre fusion technology at the core layer to overcome the bandwidth bottleneck of the LoRa protocol, ensuring efficient and stable large data transmission. The proposed three-layer joint optimisation mechanism, comprising load-aware AODV routing, power adaptation algorithms, and time-slot scheduling, dynamically adjusts network paths, transmission power, and time slots, effectively improving system throughput, reducing delays, and optimising energy efficiency. Simulation and field test results demonstrate significant improvements in throughput, delay, and energy efficiency compared to traditional LP-WMN systems, with enhanced system stability and reliability. This system provides a reliable communication foundation for future IoT applications, such as smart grids. Copyright © The Author(s) 2026.
A37: R036 | B37: S1 | C37: LoRa Mesh Network for Overhead Transmission Line Monitoring | D37: 2022 | E37: Conference paper | F37: Gemeda, D.B.; Lehner, M.; Rauh, P.; Stork, W. | G37: 2022 International Conference on Information and Communication Technology for Development for Africa, ICT4DA 2022 | H37: 10.1109/ict4da56482.2022.9971324 | I37: Include | K37: 2.1 | L37: PROTO | M37: Low | O37: =IF(N37="",IF(I37="Include","Include",J37),N37) -> Include | P37: In the last years, low power wide area networks (LP-WANs) have been developed to efficiently collect small amounts of data. Current LPWANs use a star topology, where all the traffic is sent to a central gateway. This makes them easy to implement and very energy efficient, but the coverage area of each gateway is limited and might not be sufficient for all applications. Especially for far-stretching infrastructure projects like transmission lines or pipelines, this architecture is very inefficient. The task of monitoring asset status and optimizing asset utilization for a power grid stretched over hundreds of thousands of kilometers seems costly, if not impossible. For these applications, low-power wireless mesh networks (LPWMNs) are a topic in current research. This paper develops, implements, and evaluates a novel approach for monitoring static structures with a wireless mesh network based on the LoRa (long-range) modulation from Semtech, which overcomes the limitations of traditional LPWANs. The performance of the proposed protocol was analyzed first by simulation and then with a demonstrator network on the university campus. The findings indicate that the proposed network achieves a sufficiently high packet delivery ratio (PDR) to enable the monitoring of large structures. © 2022 IEEE.
A38: R037 | B38: S1 | C38: Optimizing Power Grid Operations with IoT-Based Distribution Transformer Monitoring System | D38: 2024 | E38: Conference paper | F38: Yadav, A.; Gupta, K.; Rajput, S.K. | G38: 2024 IEEE International Students' Conference on Electrical, Electronics and Computer Science, SCEECS 2024 | H38: 10.1109/sceecs61402.2024.10481946 | I38: Exclude | J38: EC6 | O38: =IF(N38="",IF(I38="Include","Include",J38),N38) -> EC6 | P38: The paper discusses the development of a control and monitoring system for distribution transformers using IoT-based solutions. The Indian power grid is one of the largest in the world and is rapidly expanding, creating a complex mesh network. The existing SCADA system provides data to the system operator for steady-state operation, but there is a need for real-time data at the distribution level. Distribution transformers are the heart of the electrical grid, and monitoring them is crucial to prevent power outages. The proposed system uses IoT and embedded systems to monitor electrical parameters such as voltage, current, and power, and sends telemetry data to a gateway that accumulates data from other nodes and relays it to the substation. The system also includes a local dashboard for each substation and an upper layer central dashboard that collectively displays data from all substations. The system follows a three-layer architecture, with sensing nodes attached to transformers measuring electrical parameters and transmitting data to the gateway using communication modules. The communication layer processes, stores, and connects to the application layer, where the data is displayed on dashboards and can be shared with upper levels and other legacy systems using APIs with real time monitoring using MQTT and Node-RED. © 2024 IEEE.
A39: R038 | B39: S1 | C39: BST-ID: A Variable-Length Binary Spatiotemporal ID Scheme for Hierarchical and Bandwidth-Constrained Systems | D39: 2025 | E39: Conference paper | F39: Nagasawa, Y.; Yaguchi, Y. | G39: Conference Proceedings - IEEE International Conference on Systems, Man and Cybernetics | H39: 10.1109/smc58881.2025.11343277 | I39: Exclude | J39: EC6 | O39: =IF(N39="",IF(I39="Include","Include",J39),N39) -> EC6 | P39: We propose BST-ID, a variable-length binary spatiotemporal identifier tailored for hierarchical and bandwidth-constrained systems such as LoRa-based drone networks. Unlike traditional spatial indices that treat time as an auxiliary attribute, BST-ID encodes four-dimensional coordinates (x, y, h, t) with independently adjustable resolution, enabling compact and semantically adaptive representation. The identifier includes a binary header and bit-encoded coordinates, enabling prefix filtering and low-overhead communication with anisotropic control. The format is suitable for edge devices operating in multi-hop LPWAN environments. We implemented BST-ID and evaluated it against GeoHash and Google S2, demonstrating compactness (13 bytes average), encoding speed, and flexible prefix queries. Furthermore, we discuss its potential for decentralized data exchange, including blockchain integration and Lightning Network micropayments, where each ID acts as a hash-stable, time-scoped transaction reference. BST-ID thus offers a scalable, query-efficient, and token-aware foundation for distributed sensing, routing, and autonomous information sharing. © 2025 IEEE.
A40: R039 | B40: S1 | C40: LoRaMesher: An open-source library for multi-hop LoRa mesh networks | D40: 2026 | E40: Journal article | F40: Miquel Solé, J.; Freitag, F.; Baig, R. | G40: SoftwareX | H40: 10.1016/j.softx.2026.102570 | I40: Include | K40: 2.1 | L40: PROTO | M40: High | O40: =IF(N40="",IF(I40="Include","Include",J40),N40) -> Include | P40: LoRaMesher is an open-source C++ library that enables multi-hop mesh networks over LoRa communication on ESP32 microcontroller boards. The library implements a proactive distance-vector routing protocol that maintains routing tables on each node and provides unicast, broadcast, and reliable message delivery, including fragmentation and reassembly for large payloads. LoRaMesher leverages RadioLib for radio access and FreeRTOS for task scheduling, and integrates with PlatformIO for development. By allowing LoRa devices to communicate directly in a mesh network, rather than via LoRaWAN gateways, the library enables fully distributed applications on low-power IoT nodes. This paper describes the LoRaMesher software, its architecture, main functionalities, and usage examples, and discusses its relevance for research and applied IoT deployments. © 2026 The Author(s).
A41: R040 | B41: S1 | C41: An Energy-Efficient LoRa Multi-Hop Protocol through Preamble Sampling | D41: 2023 | E41: Conference paper | F41: Leenders, G.; Ottoy, G.; Callebaut, G.; Van Der Perre, L.; De Strycker, L. | G41: IEEE Wireless Communications and Networking Conference, WCNC | H41: 10.1109/wcnc55385.2023.10118770 | I41: Include | K41: 2.1 | L41: PROTO | M41: Medium | O41: =IF(N41="",IF(I41="Include","Include",J41),N41) -> Include | P41: Recent works have focused on utilizing LoRa to establish long-range and low-power connections between internet of things (IoT) nodes and gateways. A multi-hop scheme opens opportunities to greatly increase coverage in situations with adverse propagation effects or thin gateway deployment. In this work, we propose a multi-hop LoRa-based protocol tailored to battery-powered IoT devices. The protocol uses a combination of preamble sampling and dynamic payload aggregation to improve energy efficiency. In contrast to prior work, a fine-grained energy model of the devices is considered, impacting the design choices in all protocol layers, i.e., application, medium access control (MAC), and routing layer. The protocol is implemented in C and made public in open source. A first experiment indicates a high packet delivery ratio and showcases the dynamic aggregation feature. © 2023 IEEE.
A42: R041 | B42: S1 | C42: Development of a Robust Emergency Communication System Utilizing LoRa and GPS with Multi-Hop Routing | D42: 2024 | E42: Conference paper | F42: Kumaran, U.; Umah, B.; Reddy, P.P.; Shruthi, P.S.; Tharneesh, P. | G42: 2nd International Conference on Self Sustainable Artificial Intelligence Systems, ICSSAS 2024 - Proceedings | H42: 10.1109/icssas64001.2024.10760890 | I42: Exclude | J42: EC7 | O42: =IF(N42="",IF(I42="Include","Include",J42),N42) -> EC7 | P42: Conventional communication methods such as mobile phones, satellite communication, and Wi-Fi face significant challenges in remote or underserved areas. Mobile phones often fail due to low signals or lack of towers, satellite communication is prohibitively expensive, and Wi-Fi cannot cover large distances. This research explores the use of LoRa (Long Range) technology combined with a multi-hop communication technique to address these issues. LoRa's long-range capabilities and low power consumption make it ideal for reliable communication in challenging environments and in contrast to GSM which calls for a subscription and is based on mobile infrastructure, LoRa operates independently and is cost-effective. By implementing a multi-hop strategy, messages are relayed through multiple nodes, significantly extending the communication range. This paper also addresses and resolves issues such as infinite looping in message passing by incorporating unique identifiers and timestamps to ensure message integrity. Performance evaluations demonstrate substantial improvements in communication reliability and range extension, establishing this method as a cost-effective and efficient alternative to traditional communication technologies. © 2024 IEEE.
A43: R042 | B43: S1 | C43: Improving the Capacity of a Mesh LoRa Network by Spreading-Factor-Based Network Clustering | D43: 2019 | E43: Journal article | F43: Zhu, G.; Liao, C.-H.; Sakdejayont, T.; Lai, I.-W.; Narusue, Y.; Morikawa, H. | G43: IEEE Access | H43: 10.1109/access.2019.2898239 | I43: Include | K43: 2.1 | L43: PROTO | M43: Medium | O43: =IF(N43="",IF(I43="Include","Include",J43),N43) -> Include | P43: LoRa is a low-power long-range IoT standard that uses the chirp spread spectrum technique, and we have strived to further extend its coverage by utilizing the direct device-to-device (D2D) links to construct a multi-hop relay network. In LoRa, the spreading factor (SF) is an important parameter, which not only provides great flexibility between the data rate and sensitivity but also presents a new dimension for multiple accesses. Our approach to improving the capacity of a multihop LoRa network is to attempt to off-load the data traffic into several subnets by utilizing this multiple-access dimension. Each subnet rooted at a sink node is allocated a specific SF on the basis of network clustering. This enables packet transmission in parallel with multiple SFs to become feasible. To allow such parallel transmissions, our considerations are: 1) ensuring the connectivity of all subnets; 2) off-loading the traffic according to the number of nodes, data rates, and network topologies of each subnet; and 3) shortening the airtime of each subnet by reducing the hop count. Toward these objectives, we present a tree-based SF clustering algorithm (TSCA) to conduct SF allocation in a multihop LoRa network. The TSCA focuses on balancing the airtime between the subnets while ensuring connectivity. Furthermore, we use simulations to show that our approach can significantly increase the network performance compared with other approaches. We additionally deploy a real-chip experiment to evaluate the feasibility of parallel transmission in practice. © 2019 IEEE.
A44: R043 | B44: S1 | C44: LoRa for multihop communication in internet of underground things under fading environments | D44: 2025 | E44: Journal article | F44: Manzil, I.I.J.; Khalil, R.A.; Saeed, N. | G44: Internet of Things and Cyber-Physical Systems | H44: 10.1016/j.iotcps.2025.05.001 | I44: Include | K44: 2.1 | L44: EVAL | M44: Low | O44: =IF(N44="",IF(I44="Include","Include",J44),N44) -> Include | P44: This paper investigates the suitability of LoRa wireless technology for reliable underground-to-aboveground communication in the context of sustainable agricultural monitoring. We comprehensively analyze LoRa's performance in single-hop and multi-hop scenarios, considering complex environmental conditions and path loss. Mathematical expressions for the bit error rate (BER) are derived under both additive white Gaussian noise (AWGN) and Rayleigh fading, including multi-hop networks with decode-and-forward relays. Simulations under realistic Rayleigh fading scenarios validate our theoretical models. Our findings demonstrate that multi-hop LoRa networks significantly outperform single-hop systems in challenging underground environments, underscoring LoRa's potential for enhancing sustainability in various subterranean Internet of Underground Things (IoUT) agricultural applications. © 2025 The Authors
A45: R044 | B45: S1, S2 | C45: Exploiting Underground Mine Topology for Resilient Concurrent LoRa Mesh Emergency Communications: Architecture, Protocol Design, and Performance Analysis | D45: 2026 | E45: Journal article | F45: Anabi, H.K.; Frimpong, S.; Raza, M.A. | G45: Sensors | H45: 10.3390/s26123701 | I45: Include | K45: 2.1 | L45: PROTO | M45: Medium | O45: =IF(N45="",IF(I45="Include","Include",J45),N45) -> Include | P45: Underground mine emergencies compromise fixed communication infrastructure exactly when situational awareness is most critical for effective rescue operations. Existing LoRa mesh protocols fail in underground mines because they ignore the structured topology of tunnel networks, specifically the waveguide effect along straight galleries, severe signal discontinuity at junctions, and the dead-end geometry of working faces. This paper presents the Topology-Aware Concurrent LoRa (TACL) mesh protocol, in which each node autonomously infers its structural role from local RF observations and packet header information, without GPS, pre-loaded mine maps, or central coordination. Role classification resolves the contender estimation problem (Formula presented.) left open in the prior concurrent transmission literature, enabling provably bounded timing offsets before transmission. TACL assigns a spreading factor (SF)12 to dead-end source nodes for maximum link robustness and SF7–SF10 to relay nodes to create the inter-SF orthogonality margin required for concurrent decoding at junction nodes. Monte Carlo simulation of over 2000 trials yields TACL a PDR of 80.5% versus near-zero for all three baselines, confirming that topology-aware SF diversity is the necessary and sufficient mechanism to prevent junction collision collapse. Hardware deployment at the Missouri S&T Experimental Mine yields a 4.0× PDR improvement over the topology-agnostic concurrent transmission (CT)-fixed baseline, a median end-to-end latency of 1815 ms with 84× tighter latency spread than ALOHA-based protocols and 2.5× lower energy per delivered packet. These results establish that explicit exploitation of underground mine topology is essential for reliable, predictable, and energy-efficient emergency mesh communications in post-disaster underground mine scenarios. © 2026 by the authors.
A46: R045 | B46: S1 | C46: Evaluating Duty-Cycle Enforcement in Distance-Vector LoRa Mesh Networks: A Cross-Layer ns-3 Study | D46: 2026 | E46: Conference paper | F46: Arroyo, D.; Sobarzo, S.; Saavedra, G. | G46: 2026 IEEE International Mediterranean Conference on Communications and Networking, MeditCom 2026 | H46: 10.1109/meditcom67211.2026.11641097 | I46: Include | K46: 2.1 | L46: PROTO | M46: High | O46: =IF(N46="",IF(I46="Include","Include",J46),N46) -> Include | P46: Multi-hop LoRa (LoRa mesh) can extend coverage and resilience beyond LoRaWAN star topologies, but its end-to-end performance degrades when duty-cycle (DC) constraints are enforced and traffic is no longer sporadic. However, many LoRa mesh evaluations either do not enforce DC explicitly or do not record metrics that connect DC enforcement with control-plane degradation. This paper evaluates the impact of DC enforcement in a cross-layer LoRa mesh stack with proactive Distance-Vector (DV) routing that advertises routes through a compact scalar score and a CSMA/CA MAC based on Channel Activity Detection (CAD), with explicit 1% DC applied to both data and beacons. We evaluate this stack under any-to-any traffic in a 1 ~km2 area for network sizes N=9,16,25,36,49, and 64 randomly located nodes, under low and medium loads, and 10 seeds per configuration (240 runs). Results show that enabling DC systematically reduces the end-to-end delivery ratio (DR): for N=25 it drops from 0.958 to 0.438 under low load and from 0.159 to 0.058 under medium load, while for N=64 the relative impact is smaller (from 0.399 to 0.314 and from 0.051 to 0.039) due to a transition to a contention-dominated regime. Control-plane logging is consistent with this mechanism: DC reduces beacon health (Hb), which is accompanied by DV route expirations and more no-route events, linking DC enforcement to end-to-end losses. © 2026 IEEE.
A47: R046 | B47: S1 | C47: Implementation of a LoRaMesh Network and Verification of Its Effectiveness through Demonstration Experiments | D47: 2025 | E47: Conference paper | F47: Uehara, D.; Tsukamoto, K. | G47: GCCE 2025 - 2025 IEEE 14th Global Conference on Consumer Electronics | H47: 10.1109/gcce65946.2025.11275080 | I47: Include | K47: 2.1 | L47: EVAL | M47: Medium | O47: =IF(N47="",IF(I47="Include","Include",J47),N47) -> Include | P47: LoRaWAN is widely used in smart agriculture and smart cities for its low power consumption, long-range communication, and cost efficiency. However, its effectiveness declines in environments with dense buildings or forests, where obstacles impede communication. To address this, we propose and evaluate a LoRaWAN-based Mesh (LoRaMesh) Network. We compare the maximum communication distance achievable in a one-hop scenario with obstacles to that in a two-hop scenario using a relay node. Our system uses three Arduino units with LoRa Shields, configured as transmitter, relay, and receiver nodes, respectively, to form a mesh topology. Experiments are conducted in two environments: one with a clear line of sight and another with dense obstacles. In the clear environment, the relay increases the maximum communication distance by 1.5 km, while in the obstacle-rich one, the increase is 420 m-about one-third of that in the clear environment. These results show that mesh networking can effectively extend LoRaWAN coverage even in an obstructed environment, but the degree of improvement is highly dependent on the environment surrounding the receiver nodes. © 2025 IEEE.
A48: R047 | B48: S1 | C48: ArcLoRaM: Power-Aware LoRa Mesh Protocol for Remote Monitoring | D48: 2025 | E48: Conference paper | F48: Langlais, S.; Gottschalk, E.; Petersen, M.N. | G48: Proceedings of the IEEE World Forum on Internet of Things, WF-IoT | H48: 10.1109/wf-iot64238.2025.11270542 | I48: Include | K48: 2.1 | L48: PROTO | M48: Medium | O48: =IF(N48="",IF(I48="Include","Include",J48),N48) -> Include | P48: Environmental monitoring in the Arctic presents extreme challenges due to its vast, infrastructure-sparse terrain, harsh climate, and strict environmental regulations. Traditional communication methods such as satellite links or manual data retrieval are power-hungry, costly, or operationally impractical. In response, we introduce ArcLoRaM, a custom mesh protocol for ultra-low-power, long-range data transmission using sub-Ghz LoRa technology. ArcLoRaM is designed specifically for remote deployments where node autonomy and longevity are critical. It combines a hybrid mesh-of-stars topology with a time-synchronized TDMA communication scheme, decentralized power-aware routing, and self-healing capabilities. The protocol dynamically balances network load based on battery levels and hop distances, ensuring long-term operation while avoiding communication bottlenecks. We validate ArcLoRaM through simulations that analyze data throughput, collision probability, and energy efficiency under realistic regulatory constraints. Benchmark scenarios demonstrate the protocol's ability to scale from compact clusters to wide-area deployments exceeding 30,000 square kilometers, as well as its suitability for low-data-rate applications with minimal infrastructure. These results confirm that ArcLoRaM enables reliable and sustainable data collection in Arctic and similarly challenging environments. © 2025 IEEE.
A49: R048 | B49: S1 | C49: Energy-Saving Routing Protocols for Smart Cities | D49: 2022 | E49: Journal article | F49: Medeiros, D.D.F.; Souza, C.P.D.; Carvalho, F.B.S.D.; Lopes, W.T.A. | G49: Energies | H49: 10.3390/en15197382 | I49: Include | K49: 2.1 | L49: PROTO | M49: Low | O49: =IF(N49="",IF(I49="Include","Include",J49),N49) -> Include | P49: In recent decades, expansion in urban areas has faced issues such as management of public waste, noise, mobility, and air quality, among others. In this scenario, Internet of Things (IoT) and Wireless Sensor Network (WSN) scenarios are being considered for Smart Cities solutions based on the deployment of wireless remote sensor nodes to monitor large urban areas. However, as the number of nodes increases, the amount of data to be routed increases significantly as well, meaning that the choice of the data routing process has great importance in terms of the energy consumption and lifetime of the network. In this work, we describe and evaluate the energy consumption of routing protocols for WSN-based Smart Cities applications in LoRa-based mesh networks, then propose a novel energy-saving radio power adjustment (RPA) routing protocol. The Cupcarbon network simulator was used to evaluate the performance of different routing protocols in terms of their data package delivery rate, average end-to-end delay, average jitter, throughput, and load consumption of battery charge. Additionally, a novel tool for determining the range of nodes based on the Egli propagation model was designed and integrated into Cupcarbon. The routing protocols used in this work are Ad Hoc On-Demand Distance Vector (AODV), Dynamic Source Routing (DSR), and Distance Vector Routing (DVR). Our simulation results show that AODV presents the best overall performance, DSR achieves the best results for power consumption, and DVR is the best protocol in terms of latency. Finally, the proposed RPA routing protocol presents power savings of 11.32% compared to the original DSR protocol. © 2022 by the authors.
A50: R049 | B50: S1 | C50: Enabling RPL multihop communications based on LoRa | D50: 2017 | E50: Conference paper | F50: Sartori, B.; Thielemans, S.; Bezunartea, M.; Braeken, A.; Steenhaut, K. | G50: International Conference on Wireless and Mobile Computing, Networking and Communications | H50: 10.1109/wimob.2017.8115756 | I50: Include | K50: 2.1 | L50: PROTO | M50: Medium | O50: =IF(N50="",IF(I50="Include","Include",J50),N50) -> Include | P50: New Long-Range radio technologies have recently emerged in the IoT landscape. These technologies work in the Sub-GHz bands, allowing low-power communications over long distances. They are typically based on star-topology networks, where nodes send the data directly to a base station connected to the Internet. One of such technologies is LoRa. Enabled LoRa-based multihop communications would open up new possibilities. In this paper we present a solution allowing to have multihop LoRa communications. This is done by means of a newly designed MAC protocol (RLMAC), used to select the Spreading Factor for each available neighbor. The proposed Objective Function used by RPL will therefore be able to select the routing path that minimizes time on-air. By selecting the path with the lowest time on-air, the power consumption can be decreased, enlarging network lifetime. Preliminary validation tests are also presented in the paper. © 2017 IEEE.
A51: R050 | B51: S1 | C51: Prospects and Challenges in UAV-Based Communication for Disaster Management | D51: 2025 | E51: Conference paper | F51: Haldar, C.; Podder, S. | G51: Proceedings of 2025 IEEE Artificial Intelligence for Computing, Astronomy, and Renewable Energy, AICARE 2025 | H51: 10.1109/aicare66005.2025.11402816 | I51: Exclude | J51: EC6 | O51: =IF(N51="",IF(I51="Include","Include",J51),N51) -> EC6 | P51: Natural disasters like earthquakes, floods and wild fires are responsible for enormous human and economic causalities. Traditional methods of assessing such as ground reconnaissance, manned aerial observation and satellite imagery are usually time-consuming, unsafe and unsuitable in dynamic disaster situations. UAVs have demonstrated their effectiveness in disaster management, such as for rapid and agile high-resolution data acquisition to support situational awareness, damage inspection and the relief supply chain. This paper provides a detailed study of conventional disaster management system and various technologies of UAV communication architectures for disaster management. It also discusses severe issues like restricted range, infrastructure dependency, network overload, and signal degradation due to interference in the environment. To address these limitations, we suggest a hybrid UAV communication architecture integrating satellite, LoRa, and FANET-based mesh networking. The design enables UAVs to flexibly transition between communication modes according to mission requirements, Active level of resources (AoR), geography, and available battery stocks. The architecture is complemented by optimized routing approaches that are individually designed for different communication types, contributing to low-latency, fault-tolerant and energy-efficient data transmission. This method dramatically reduces scale resistance, flexibility and the agileness of real-time data-intensive using. By bridging current communication gaps and facilitating real-time information sharing, the proposed system provides a sustainable and resilient solution to improving UAV-based disaster response operations. The research opens doors for future potential research work in field deployment, edge computing, and integrating artificial intelligence-assisted decision-making, and autonomous multi-agent-based disaster management systems. ©2025 IEEE.
A52: R051 | B52: S1 | C52: Multi-copy, Spatially-Confined Broadcast Routing to Support Message Delivery with Handshaking in Multi-hop LoRa Network | D52: 2025 | E52: Conference paper | F52: Wibawa, Y.P.; Yogiswara, I.P.A.; Kusuma, A.A.N.A.; Agastani, T.; Pinastiko, W.S.; Irawan, D.; Hamdani, M.; Samudro, M.A. | G52: International Conference on Radar, Antenna, Microwave, Electronics, and Telecommunications, ICRAMET | H52: 10.1109/icramet67419.2025.11350147 | I52: Include | K52: 2.1 | L52: FLOOD | M52: Medium | O52: =IF(N52="",IF(I52="Include","Include",J52),N52) -> Include | P52: Although LoRaWAN standard has recently issued relay specification used for multi-hop communication, its application has not been prevalent. This paper proposes multi-hop capability, coupled with multi-copy, spatially confined-broadcast message routing for Lora-based network. To reduce the impact of medium access contention, local slotted Aloha is utilized, and enhance it with sender-aware forwarding scheme. We also extend its capability to facilitate handshaking communication. Developing this capability aims at larger network coverage, complex network topology, and provides reliable message delivery when poor links are expected within the network. We developed multi-hop-capable LoRa devices prototype and deploy them in a meshtopology network. Packet delivery rate and latency are evaluated. The result shows that our developed multi-hop capability, coupled with spatially-confined broadcast routing protocol for message delivery and handshaking, can achieve above 95 percent packet delivery rate with acceptable latency in mesh network and effectively mitigate the impact of poor link within the network © 2025 IEEE.
A53: R052 | B53: S1 | C53: Lora-hybrid: A LoRaWAN based multihop solution for regional microgrid | D53: 2019 | E53: Conference paper | F53: Zhou, W.; Tong, Z.; Dong, Z.Y.; Wang, Y. | G53: 2019 IEEE 4th International Conference on Computer and Communication Systems, ICCCS 2019 | H53: 10.1109/ccoms.2019.8821683 | I53: Include | K53: 2.1 | L53: RELAY | M53: Low | O53: =IF(N53="",IF(I53="Include","Include",J53),N53) -> Include | P53: Low Power Wide Area Network (LPWAN), such as LoRaWAN, has become the most fast-growing Internet of Things wireless solution in recent years. In April 2018, the city of Newcastle in Australia has rolled out a smart city initiative by adopting LoRaWAN. With its long-range, low power and low-cost features, it is ideal for a regional smart grid as an extension of the smart city project. Whereas, LoRaWAN single-hop topology hinders its further expansion because this mode would require more gateway installation to extend network coverage. It is foreseeably cost-effective if the message can be relayed by end devices while not sacrificing the performances. In this paper, we present a novel architecture by utilizing LoRaWAN MAC (media Access control) layer and application layer to overcome obstructions, such as buildings and hills, extending radio coverage. During our field test, we receive encouraging performance outcome when putting the system to test in a simulated grid environment. © 2019 IEEE.
A54: R053 | B54: S1 | C54: LoRa as a Mesh Networking Technology | D54: 2025 | E54: Conference paper | F54: Branch, P. | G54: International Conference on Information Networking | H54: 10.1109/icoin63865.2025.10992870 | I54: Include | K54: 2.1 | L54: FLOOD | M54: High | O54: =IF(N54="",IF(I54="Include","Include",J54),N54) -> Include | P54: Although LoRa is primarily known for the long distances it can cover it also has characteristics that make it attractive as a relay technology in mesh networks. Unlike other wireless network technologies where concurrent transmission by two or more nodes results in corruption of both messages at the receiver, a LoRa receiver synchronises with just one transmitter and treats any other concurrent transmission as noise. This greatly simplifies the design of network relays in that they do not need complex schemes to deal with contention. It also reduces the number of copies of a message received at the destination. This approach also reduces latency when compared with schemes such as CSMA/CA used in other networks. However, there is a cost in terms of reduced Signal to Noise Ratio (SNR) which has a consequent impact on message error rate at the receiver. In this paper we use a two hop LoRa network comprising a transmitter, multiple relays and a receiver to evaluate the impact of concurrent transmission on latency, the number of packets forwarded, the SNR, the Received Signal Strength Indicator (RSSI) and the error rate as the number of relays forwarding a copy of the same message is increased. We observed that LoRa receivers synchronise with just one transmitter and forward only one copy of a message. We also observed that there is negligible latency regardless of the number of relays at each hop. However, we see an impact on SNR and successful message delivery. SNR reduces as the number of relays transmitting concurrently increases and successful frame delivery deteriorates rapidly once more than four relays forward a message with 45% messages lost when there are seven relays. © 2025 IEEE.
A55: R054 | B55: S1 | C55: Building Multihop LoRa Network for Enhanced Range and Quality Transmission of Healthcare Data | D55: 2023 | E55: Conference paper | F55: Paria, S.; Nath, S.; Mallick, C.; Das, D. | G55: 2023 8th International Conference on Computers and Devices for Communication, CODEC 2023 | H55: 10.1109/codec60112.2023.10466170 | I55: Exclude | J55: EC7 | O55: =IF(N55="",IF(I55="Include","Include",J55),N55) -> EC7 | P55: Efforts towards a cheap yet efficient health care infrastructure for remote rural areas requires longrange remote sensing communication over large areas. However, establishing efficient healthcare infrastructure in remote areas in developing countries like India, continues to be hampered by the lack of cost-effective and scalable IoT solutions. In this paper, a technique of multihop LoRa Network is built using relay for quality health data transmission for low-cost low power solution. © 2023 IEEE.
A56: R055 | B56: S1 | C56: Enabling direct messaging from LoRa to ZigBee in the 2.4 GHz Band for industrial wireless networks | D56: 2019 | E56: Conference paper | F56: Shi, J.; Chen, X.; Sha, M. | G56: Proceedings - IEEE International Conference on Industrial Internet Cloud, ICII 2019 | H56: 10.1109/icii.2019.00043 | I56: Exclude | J56: EC6 | O56: =IF(N56="",IF(I56="Include","Include",J56),N56) -> EC6 | P56: IEEE 802.15.4-based wireless sensor-actuator networks (WSANs) have been quickly adopted by process industries in recent years because of their significant role in improving industrial efficiency and reducing operating cost. Battery-powered wireless modules can be used to easily and inexpensively retrofit existing sensors and actuators in industrial facilities without running cabling for communication and power. Wireless-enabled sensors, actuators, and controllers form a low-power multi-hop mesh network to exchange sensing data and control commands. Today, industrial WSANs are becoming tremendously larger and more complex than before. A large and complex mesh network is hard to manage and inelastic to change once the network is deployed. Besides, flooding-based time synchronization and information dissemination introduce significant communication overhead to the network. More importantly, the deliveries of urgent and critical information such as emergency alarms suffer long delay, because those messages must go through the hop-by-hop transport. A promising solution to overcome those limitations is to enable the direct messaging from a long-range radio to an IEEE 802.15.4 radio. Then messages can be delivered to all field devices in a single-hop fashion. This paper presents our study on enabling the cross-technology communication (CTC) from LoRa to ZigBee (IEEE 802.15.4) using the energy emission of the LoRa radio in the 2.4 GHz band as the carrier to deliver information. Experimental results show that our CTC approach provides reliable communication from LoRa to ZigBee with the throughput of up to 576.80bps and the bit error rate (BER) of up to 5.23% in the 2.4 GHz band. © 2019 IEEE.
A57: R056 | B57: S1 | C57: Hierarchical Adaptive Energy-Efficient Protocol for LoRa-Mesh Networks: A Data Fusion and Wake-on-Air Based Approach | D57: 2026 | E57: Journal article | F57: Li, X.; Chen, G.; Shang, J.; Qi, H. | G57: IEEE Internet of Things Journal | H57: 10.1109/jiot.2026.3732880 | I57: Include | K57: 2.1 | L57: PROTO | M57: Low | O57: =IF(N57="",IF(I57="Include","Include",J57),N57) -> Include | P57: To address short battery lifetime, high energy consumption, collision-prone network construction, and limited abnormal-event responsiveness in large-scale LoRa-Mesh networks for fine particulate matter (PM2.5) monitoring, this study proposes a Hierarchical Adaptive Energy-Efficient (HAEE) protocol. HAEE jointly integrates Wake-on-Air (WoA)-assisted hierarchical construction, Data-Driven Adaptive Sampling (DDAS), and hierarchical abnormal-data forwarding. WoA assigns nodes to different layers according to their hop distance from the gateway and avoids blind network-wide flooding during initialization. DDAS dynamically adjusts the wake-up cycles of neighboring nodes according to PM2.5 thresholds and a topology-derived normalized Local Spatial Correlation (LSC) control index, reducing redundant sensing and communication under stable conditions. Abnormal data are forwarded to the gateway through Received Signal Strength Indicator (RSSI)-based upper-layer relay selection. Thirty-seed Monte Carlo simulations show that HAEE achieves shorter initialization time and lower packet collision rate than representative hierarchical and proactive LoRa-Mesh baselines. Under the unified state-based energy model, HAEE reduces network energy consumption over the 300-s evaluation window by approximately 84.7% at 300 nodes compared with the simultaneous wake-up strategy. The LSC-aware DDAS mechanism reduces simulated daily energy consumption per node from approximately 284 J/day to 78 J/day across the evaluated LSC range. In a synthetic spatio-temporal PM2.5 simulation, HAEE-DDAS achieves approximately 95.2% data fidelity and 99.9% abnormal-event recall. HAEE also improves network lifetime and delivery reliability under different LoRa physical-layer settings, traffic loads, channel conditions, and node-failure scenarios. These results establish the effectiveness of HAEE for long-term large-scale PM2.5 monitoring under the stated simulation configuration. © 2014 IEEE.
A58: R057 | B58: S1 | C58: Multi-Hop LoRa Communication for Natural Disaster Management: A Field Test | D58: 2023 | E58: Conference paper | F58: Marrara, G.; Suraci, C.; Tropeano, A.; Bombino, G.; Araniti, G. | G58: Proceedings - 2023 IEEE 8th International Conference on Information and Communication Technologies for Disaster Management, ICT-DM 2023 | H58: 10.1109/ict-dm58371.2023.10286960 | I58: Include | K58: 2.1 | L58: EVAL | M58: Medium | O58: =IF(N58="",IF(I58="Include","Include",J58),N58) -> Include | P58: Natural disasters present a significant challenge to emergency response teams, as they frequently disrupt communication infrastructure and hinder situational awareness. Italy's morphological structure places roughly 14% of its territory at risk for flooding. In particular, Calabria is considered the region most exposed to the high-risk scenario; therefore, to manage the hydrogeological risk many check-dams have been built, whose constant and timely monitoring is crucial. The integration of the Internet of Things (IoT) paradigm and Long-Range radio (LoRa) technology offers a potential solution for ensuring resilient communication networks in the face of natural disasters. This paper presents a field test that implements a multi-hop device-to-device (D2D) LoRa network, in which nearby devices communicate directly through LoRa technology, to optimize the process of updating the ARCHIMEDE database, a WebGIS archive of hydraulic intervetions, that can be interfaced with the Territorial Information Systems used by the Civil Protection of the Calabria Region in Italy. © 2023 IEEE.
A59: R058 | B59: S1 | C59: Forest Fire Monitoring and Energy Optimization Based on LoRa-Mesh Wireless Communication Technology | D59: 2025 | E59: Journal article | F59: Li, Z.; Li, X.; Shang, J. | G59: Electronics (Switzerland) | H59: 10.3390/electronics14214135 | I59: Exclude | J59: EC7 | O59: =IF(N59="",IF(I59="Include","Include",J59),N59) -> EC7 | P59: Forest fire monitoring is of great significance for ecological protection and public safety. This study proposes a monitoring technology based on LoRa-Mesh (Long Range-Mesh) wireless communication, integrating temperature and humidity sensing, image acquisition, fire identification, data transmission, and energy-saving optimization. To address the limitations of traditional LoRa networks in flexibility and energy consumption, a Layered Dynamic Synchronization Energy-saving (LDSE) protocol is designed. By constructing a hierarchical network, employing implicit route exploration, multi-channel and multi-path communication, and time synchronization optimization, the protocol significantly reduces packet loss rate and system energy consumption. Experimental results demonstrate that the LDSE protocol outperforms the traditional Ad hoc On-Demand Distance Vector Routing Protocol (AODV) in terms of packet loss rate, energy consumption, and latency. Additionally, the proposed energy-saving algorithm significantly reduces system power consumption, with the node sleep-relay mode exhibiting optimal energy efficiency. Experimental verification confirms that the system achieves high reliability, low power consumption, and efficient data transmission, providing an effective IoT solution for forest fire prevention. © 2025 by the authors.
A60: R059 | B60: S1 | C60: 1st International Conference on on Computational Intelligence in Engineering Science, ICCIES 2025 | D60: 2026 | E60: Journal article | G60: Communications in Computer and Information Science | I60: Exclude | J60: EC4 | O60: =IF(N60="",IF(I60="Include","Include",J60),N60) -> EC4 | P60: The proceedings contain 31 papers. The special focus in this conference is on Computational Intelligence in Engineering Science. The topics include: PRIMO: A Privacy-Preserving Decentralized Machine Learning Algorithm; smart Harvesting: Sorting Coffee Fruit Maturity Using Deep Learning; Combining Explainable AI (XAI) and Regression Analysis to Explain Relationships in Electricity Consumption Behavior; detecting Anomalies and Defects in Integrated Circuits by Ensembling Deep Learning Models; Doctor AI: A Hybrid Model for Clinical Ocular Disease Classification; forecasting Weather: A Scenario of the Mekong Delta; melanoma Detection Using Augmented ResNet34 for High-Precision Dermoscopic Image Classification; abnormal Plums Detection Using Unsupervised Learning; Hybrid Deep Learning Model for MRI Brain Tumor Identification; leveraging Machine Learning for Accurate Order Quantity Forecasting: A Case Study of Vietnam’s Coffee Production Industry; an Attentive Deep Neuro-Fuzzy Network for Interpretable Breast Cancer Diagnosis; detection of Littering Behavior Using MobileNet and Vision Transformer; the Effectiveness of Channel and Spatial Attention for Improving Image Classification; ATMOS: IoT-Driven Air Quality Monitoring and Forecasting System Using Machine Learning and Fog Computing; leveraging Deep Neural Networks for Regional Weather Forecasting in Vietnam; detecting Abnormalities in Chest X-Ray Images by Combining Classification Methods, Object Detection, and Data Balancing; support Decision Making for Supplier Selection Using Feature Importance; Optimizing NP-Hard Problems: A Comparative Study of Metaheuristic Algorithms with Benchmark Performance Analysis; on the Performance of Downlink LoRa Networks with Fountain Codes and Diversity Techniques; Maximizing Secrecy Performance in UAV-Based Cognitive Relay Systems; Outage Performance of NOMA-Aided Multi-hop Relay Schemes in Underlay Cognitive Networks Using Fountain Codes; Energy Outage Analysis for NOMA-Based UAV-MEC with Imperfect CSI and SIC in IoT Network; Secure Edge Computing in UAV-Assisted Backscatter Communication NOMA Wireless Sensor Network with Friendly Jamming.
A61: R060 | B61: S1, S2 | C61: LoRaMPP: Optimizing IoT Messaging Efficiency Using Unlicensed Spectrum | D61: 2026 | E61: Conference paper | F61: Sifat, F.K.; Saha, P.K.; Torikur Rahman, M.; Haque, R.; Abul Basar, M.; Nazmus Sadat, S.M.; Islam, M.A. | G61: Lecture Notes in Electrical Engineering | H61: 10.1007/978-981-92-3681-7_12 | I61: Include | K61: 2.1 | L61: PROTO | M61: Medium | O61: =IF(N61="",IF(I61="Include","Include",J61),N61) -> Include | P61: The growing demand for scalable, low-power, and flexible communication in the Internet of Things (IoT) has highlighted the limitations of existing LoRa-based protocols, particularly in infrastructure-less or energy-constrained environments. This paper presents LoRaMPP (LoRa Multi-purpose Protocol), a novel hybrid communication framework designed for energy-efficient IoT messaging over unlicensed spectrum. LoRaMPP supports dual-mode operation–gateway-based WAN communication and peer-to-peer (P2P) or mesh networking–enabling seamless adaptability across smart cities, remote agricultural zones, and disaster-prone areas. The proposed system introduces an adaptive MAC layer, flexible packet structure, lightweight mesh routing, and mobile user access via USB Type-C or BLE. It incorporates power optimization techniques including duty-cycled sleep scheduling, adaptive spreading factor (SF) selection, and collision-aware backoff mechanisms. Security is enhanced with optional AES-128 encryption and message integrity checks. Comprehensive evaluation on ESP32-based nodes with SX1278 transceivers, as well as custom simulations across varied environments, demonstrates up to 12% higher packet delivery ratio (PDR), 39% lower indoor latency, and battery lifetime extension of up to 6.8 months compared to existing protocols such as LoRaWAN, LoRaMesh, and DoLoRa. LoRaMPP was evaluated using ESP32-based nodes and SX1278 transceivers, and benchmarked against LoRaWAN, LoRaMesh, and DoLoRa. Results demonstrate improved packet delivery ratio, reduced energy consumption per byte, and lower latency, especially in infrastructure-less settings. By combining the robustness of LoRaWAN, the decentralization of LoRaMesh, the energy awareness of DoLoRa, and the accessibility of PicoWAN, LoRaMPP offers a unified and practical solution for modern IoT deployments requiring resilience, energy efficiency, and offline operability. © The Author(s), under exclusive license to Springer Nature Singapore Pte Ltd. 2026.
A62: R061 | B62: S1 | C62: Adaptive Parameters Configuration of LoRa for Multi-Hop Networks Transmission | D62: 2025 | E62: Conference paper | F62: Jumali, M.K.; Lim, K.G.; Angeline, L.; Moung, E.G.; Wang, T.; Kin Teo, K.T. | G62: 7th IEEE International Conference on Artificial Intelligence in Engineering and Technology, IICAIET 2025 | H62: 10.1109/iicaiet67254.2025.11265326 | I62: Include | K62: 2.1 | L62: PROTO | M62: Low | O62: =IF(N62="",IF(I62="Include","Include",J62),N62) -> Include | P62: This study assesses a node-autonomous Adaptive Data Rate (ADR)-like algorithm's performance in optimizing Packet Delivery Ratio (PDR) in a LoRa multi-hop network, simulated in a forestry-like environment using Python with Visualize and matplotlib at 915 MHz. Using a log-distance path loss model, a three-node setup (transmitter, relay, gateway) spans 200-1000 meters, adjusting Spreading Factor (SF10-SF12), transmission power (14-20 dBm), and bandwidth (125-250 kHz). After 300 packets, PDR remains 100% up to 400 meters, drops to 40% at 500 meters, and nears 0% at 1,000 meters, with RSSI declining from -90 dBm to -125 dBm and SNR from 30 dB to 0 dB. Energy use rises from 0-2,000 mJ to over 8,000 mJ at 1000 meters due to retransmissions. At large scale After 1,000 packets, PDR fluctuates, dropping from 100% to 0% at 0-200 meters, peaking at 50% at 300 meters, 70% at 800 meters, and falling to 10% at 600 meters. Energy consumption spikes from 2,000 mJ to 30,000 mJ between 500-700 meters, dips to 5,000 mJ at 850 meters, and rises beyond 1,000 meters. Packet collisions increase from 30 to 50 at 550-600 meters, drop to 30 at 850 meters, and surge to 300 beyond 1,000 meters due to co-channel interference. The 500-meter limit suggests optimal relay placement. While effective at short ranges, the algorithm struggles at longer distances, indicating a need for coding rate adjustments or additional relays. This study offers insights for energy-efficient LoRaWAN deployments in challenging terrains, recommending real-world validation. © 2025 IEEE.
A63: R062 | B63: S1 | C63: SF-Partition-Based Clustering and Relaying Scheme for Resolving Near–Far Unfairness in IoT Multihop LoRa Networks | D63: 2022 | E63: Journal article | F63: Mugerwa, D.; Nam, Y.; Choi, H.; Shin, Y.; Lee, E. | G63: Sensors | H63: 10.3390/s22239332 | I63: Include | K63: 2.1 | L63: PROTO | M63: Low | O63: =IF(N63="",IF(I63="Include","Include",J63),N63) -> Include | P63: Long range (LoRa) is one of the most successful low-power wide-area networking technologies because it is ideally suited for long-distance, low-bit rate, and low-power communications in the unlicensed sub-GHz spectrum utilized for Internet of things (IoT) networks. The effectiveness of LoRa depends on the link budget (i.e., spreading factor (SF), bandwidth (BW), and transmission power (TX)). Due to the near–far effect, the allocation of a link budget to LoRa devices (LDs) in large coverage regions is unfair between them depending on their distance to the GW. Thus, more transmission opportunities are given to some LDs to the detriment of other LD’s opportunities. Numerous studies have been conducted to address the prevalent near–far fairness problem. Due to the absence of a tractable analytical model for fairness in the LoRa network, however, it is still difficult to solve this problem completely. Thus, we propose an SF-partition-based clustering and relaying (SFPCR) scheme to achieve enormous LD connectivity with fairness in IoT multihop LoRa networks. For the SF partition, the SFPCR scheme determines the suitable partitioning threshold point for bridging packet delivery success probability gaps between SF regions, namely, the lower SF zone (LSFZ) and the higher SF zone (HSFZ). To avoid long-distance transmissions to the GW, the HSFZ constructs a density-based subspace clustering that generates clusters of arbitrary shape for adjacent LDs and selects cluster headers by using a binary score representation. To support reliable data transmissions to the GW by multihop communications, the LSFZ offers a relay LD selection that ideally chooses the best relay LD to extend uplink transmissions from LDs in the HSFZ. Through simulations, we show that the proposed SFPCR scheme exhibits the highest success probability of 65.7%, followed by the FSRC scheme at 44.6%, the mesh scheme at 34.2%, and lastly the cluster-based scheme at 29.4%, and it conserves the energy of LDs compared with the existing schemes. © 2022 by the authors.
A64: R063 | B64: S1 | C64: An Embedded Multi-Sensor IoT Platform for Agricultural Monitoring Using Meshtastic-Based LoRa Communication and Cloud Microservices | D64: 2026 | E64: Journal article | F64: Negulescu, C.; Borangiu, T.; Răileanu, S.; Anghel, V.-V. | G64: Sensors | H64: 10.3390/s26185839 | I64: Include | K64: 2.1 | L64: COMMUNITY | M64: High | O64: =IF(N64="",IF(I64="Include","Include",J64),N64) -> Include | P64: The paper presents a low-cost agricultural monitoring platform based on embedded IoT sensing, LoRa mesh communication, and an Edge–Fog–Cloud architecture designed for real-time environmental monitoring in smart agriculture applications. The proposed system integrates distributed sensor nodes built around the Heltec Mesh Node T114 platform, combining an nRF52840 microcontroller with an SX1262 LoRa transceiver to support low-power, long-range communication in agricultural environments. Environmental data acquisition is performed using integrated BME280 temperature, humidity, and pressure sensors, capacitive soil moisture sensors, and TEMT6000 light sensors. A custom firmware architecture extending the Meshtastic framework was developed to support sensor integration, telemetry generation, packet forwarding, and energy-aware scheduling within the LoRa mesh network. The platform combines embedded telemetry modules, intermediate routing mechanisms, and cloud-based microservices responsible for data aggregation and processing. Experimental results showed stable radio-link conditions in the tested node-to-router configuration, with RSSI values around −55 dBm and SNR values of approximately 6–7 dB. Channel utilization varied between approximately 4% and 12%, while transmission airtime utilization remained below 5%. These results support the feasibility of the proposed sensing, communication, and data-processing architecture under the tested configuration. The architecture is designed to accommodate additional sensing and routing nodes, while multi-hop performance, long-term energy consumption, and network scalability remain to be evaluated in larger deployments. © 2026 by the authors.
A65: R064 | B65: S1 | C65: Time‐Slotted Spreading Factor Hopping for Mitigating Blind Spots in LoRa‐Based Networks | D65: 2022 | E65: Journal article | F65: Iglesias‐rivera, A.; Van Glabbeek, R.; Guerra, E.O.; Braeken, A.; Steenhaut, K.; Cruz‐enriquez, H. | G65: Sensors | H65: 10.3390/s22062253 | I65: Include | K65: 2.1 | L65: RELAY | M65: Low | O65: =IF(N65="",IF(I65="Include","Include",J65),N65) -> Include | P65: It has been demonstrated that LoRa‐based wide area networks (WANs) can cover ex-tended areas under harsh propagation conditions. Traditional LoRaWAN solutions based on single-hop access face important drawbacks related to the presence of blind spots. This paper aims to tackle blind spots and performance issues by using a relaying approach. Many researchers investigating multi‐hop solutions consider a fixed spreading factor (SF). This simplifies synchronization and as-sociation processes, but does not take advantage of the orthogonality between the virtual channels (i.e., frequency, SF) that help to mitigate blind spots. This paper proposes a time‐slotted spreading factor hopping (TSSFH) mechanism that combines virtual channels and time slots into a frame struc-ture. Pseudo‐random scheduling is used inside blind spots, which simplifies the end‐devices’ communication process and network organization. The results show how collisions decrease inside blind spots when more communication opportunities become available as more relaying nodes can be listening in different cells (i.e., frequency, SF‐offset, time‐offset). This has a direct impact on the collision‐free packet delivery ratio (PDR) metric, which improves when more listening windows are opened, at the expense of faster battery depletion. © 2022 by the authors. Licensee MDPI, Basel, Switzerland.
A66: R065 | B66: S1 | C66: Node Failure Detection on a Hierarchy-Based Energy-Efficient Routing Protocol for LoRa-Mesh | D66: 2026 | E66: Conference paper | F66: Blum, L.; Rosa, L.L.; Dos Santos Roque, A.; De Freitas, E.P. | G66: 2026 IEEE International Black Seas Conference on Communications and Networking, BlackSeaCom 2026 | H66: 10.1109/blackseacom69760.2026.11598298 | I66: Include | K66: 2.1 | L66: PROTO | M66: Low | O66: =IF(N66="",IF(I66="Include","Include",J66),N66) -> Include | P66: Low-Power Wide-Area Networks (LPWANs) based on LoRa technology are widely used in Internet of Things (IoT) applications due to their long communication range and low energy consumption. While most LoRa deployments rely on star topologies, mesh networking protocols such as the Hierarchical Balanced Energy Efficient (HBEE) protocol enable multi-hop communication, extending coverage in challenging environments. However, node failures in LoRa mesh networks can significantly degrade performance when nodes continue forwarding packets through failed parents. This work proposes a lightweight failure detection mechanism for HBEE-based LoRa mesh networks. The approach uses passive overhearing to detect missing forwarding activity and applies timeout-based strategies to identify suspected node failures. When a failure is suspected, an on-demand ping message is used to confirm node availability and prevent further transmissions through inactive nodes. The proposed mechanism was evaluated experimentally using a LoRa mesh testbed. Results show that introducing failure detection improves network reliability under failure conditions, increasing the Packet Reception Rate from 79.17% to up to 86.67% without introducing significant additional energy consumption. © 2026 IEEE.
A67: R066 | B67: S1 | C67: LoRaWAN multi-hop uplink extension | D67: 2018 | E67: Conference paper | F67: Dias, J.; Grilo, A. | G67: Procedia Computer Science | H67: 10.1016/j.procs.2018.04.063 | I67: Include | K67: 2.1 | L67: RELAY | M67: Medium | O67: =IF(N67="",IF(I67="Include","Include",J67),N67) -> Include | P67: The coverage of a LoRaWAN network in a city is greatly hampered by the harsh propagation environment. Sensors are sometimes placed under the ground or in places with strong electromagnetic attenuation. Also, for users who have a contract with a network operator, installing another gateway to improve coverage of blind spots is not an option. In other cases, there is no or very weak connectivity (e.g. basements). In the present work, we design and implement a multi-hop uplink solution compatible with the LoRaWAN specification, which can act as an extension to already deployed gateways. End nodes transmit data messages to intermediate nodes, which relay them to gateways by choosing routes based on a simplified version of Destination-Sequenced Distance Vector (DSDV) routing. The routing protocol was successfully implemented and was assessed using a linear and bottleneck topology, where the Packet Reception Rate (PRR) and throughput were measured. On the bottleneck topology it was observed that the PRR of each node did not significantly vary. On the linear topology we observed that the throughput and PRR did not decrease considerably with the increase of hops. © 2018 The Authors. Published by Elsevier B.V.
A68: R067 | B68: S1 | C68: Wireless IIoT network modeling, Neural Route Mapping, and delay-aware analysis | D68: 2026 | E68: Journal article | F68: Noorwali, A. | G68: Journal of Umm Al-Qura University for Engineering and Architecture | H68: 10.1007/s43995-025-00280-4 | I68: Exclude | J68: EC6 | O68: =IF(N68="",IF(I68="Include","Include",J68),N68) -> EC6 | P68: The rapid expansion of Saudi Arabia’s industrial has created a critical demand for reliable, delay-aware communication frameworks to ensure occupational safety, real-time emergency coordination, and data-driven decision support. Traditional cellular systems often collapse under congestion, interference, or limited spectrum availability, especially in dense ndoes zones. This paper introduces a mathematically grounded Industrial Internet of Things (IIoT) model that integrates LoRa-based mesh connectivity, Voronoi-driven spatial coverage, and a Neural Route Mapping Protocol (NRMP) designed to minimize latency and interference while optimizing throughput and network lifetime. The proposed model unifies analytical design by combining (i) signal-to-interference-plus-noise ratio (SINR) constraints, (ii) queueing-based access delay modeling using M/M/1 and PCF/DCF formulations, and (iii) multi-objective optimization for energy-aware routing. Closed-form delay bounds are derived under interference and traffic load constraints, forming a theoretical foundation for delay-tolerant yet safety-critical IIoT systems. Simulation-based validation demonstrates that the NRMP model can significantly outperform standard routing schemes such as Dynamic Source Routing (DSR) in terms of throughput, energy efficiency, and latency [1, 2, 3–4]. © The Author(s) 2025.
A69: R068 | B69: S1 | C69: IoT Station for Health Monitoring in Underground Mining Using Compressive Sensing Architecture | D69: 2025 | E69: Conference paper | F69: Wahidah, I.; Shiddieqy, H.A.; Wafi, A.; Ramli, A.P.; Noor, B.R.; Amri, Y. | G69: International Conference on Artificial Intelligence in Information and Communication, ICAIIC | H69: 10.1109/icaiic64266.2025.10920859 | I69: Exclude | J69: EC7 | O69: =IF(N69="",IF(I69="Include","Include",J69),N69) -> EC7 | P69: This study addresses health and safety risks in the underground mining by developing an Internet of Things (IoT) Station using compressive sensing architecture to monitor vital parameters such as heart rate, body temperature, carbon monoxide (CO) levels, and environmental temperature in real-time manner. Data transmission is facilitated through a LoRa wireless network utilizing a star multihop topology, which allows sensor modules to first send data to a central LoRa transceiver before relaying it to a main base station. The communication module extends coverage and enhances data reliability, making it suitable for challenging underground environments. Simulation and testing demonstrated effective communication up to 1.6 km in open areas and 1 km in closed areas, with stable data transmission. This multihop approach reduces accident risks and enhances safety and productivity by ensuring comprehensive monitoring across extended areas. The Compressive Sensing architecture improves bandwidth and energy efficiency by reducing the data volume by up to 50% without losing important information. In addition, the system employs thresholding to classify conditions into 'safe,' 'alert,' and 'danger' categories based on specific ranges for humidity, CO levels, temperature, and heart rate. © 2025 IEEE.
A70: R069 | B70: S1 | C70: LTM-LoRaWAN: A Multi-Hop Communication System for LoRaWAN | D70: 2023 | E70: Journal article | F70: Al mojamed, M. | G70: Electronics (Switzerland) | H70: 10.3390/electronics12204225 | I70: Include | K70: 2.1 | L70: RELAY | M70: Medium | O70: =IF(N70="",IF(I70="Include","Include",J70),N70) -> Include | P70: Coverage limitation due to signal attenuation is one of the main challenges facing single-hop LoRaWAN when deployed in IoT applications that require low power consumption and operate over a wide area network. The challenge can be figured out using the dense deployment of typical LoRaWAN gateways to ensure devices can transfer their data to the network server successfully. However, this is considered a costly path because of the requirement of deploying a larger number of gateways. To cope with this, a multi-hop communication strategy can be utilized to extend the coverage of employed LoRaWAN networks, eliminating the need for dense gateway deployment. Thus, this paper proposes a Listen-To-Talk-based Multi-hop LoRaWAN LTM-LoRaWAN, a multi-hop relaying system for a wide area LoRaWAN network. It supports out-of-range devices to deliver their traffic to the gateway without using complex routing mechanisms or routing topology construction. Moreover, the proposed system is dynamic and does not require any special entities or assign specific tasks to specific devices. The paper provides a detailed description of the design and configuration of the proposed LTM-LoRaWAN. Using simulation, the feasibility of the proposed system was demonstrated. The evaluation result showed that the proposed system outperformed one-hop LoRaWAN and achieved better reliability in traffic delivery. © 2023 by the author.
A71: R070 | B71: S1 | C71: Multi-Hop Routing Protocols for Oil Pipeline Leak Detection Systems | D71: 2022 | E71: Journal article | F71: Alhomyani, H.; Fadel, M.; Dimitriou, N.; Bakhsh, H.; Aldabbagh, G.; Alkhuraiji, S. | G71: Electronics (Switzerland) | H71: 10.3390/electronics11132078 | I71: Include | K71: 2.1 | L71: PROTO | M71: Low | O71: =IF(N71="",IF(I71="Include","Include",J71),N71) -> Include | P71: In recent years, various applications have emerged requiring linear topologies of wireless sensor networks (WSN). Such topologies are used in pipeline (water/oil/gas) monitoring systems. The linear structure has a significant impact on network performance in terms of delay, throughput, and power consumption. Regarding communication efficiency, routing protocols play a critical role, considering the special requirements of linear topology and energy resources. Therefore, the chal-lenge is to design effective routing protocols that can address the diverse requirements of the monitoring system. In this paper, we present various wireless communication technologies and existing leak detection systems. We review different routing protocols focusing on multi-hop hierarchical protocols, highlighting the limitations and design issues related to packet routing in linear pipeline leak detection networks. Additionally, we present a LoRa multi-hop model for monitoring above-ground oil pipelines. A set of model parameters are identified such as the distance between sensors. In addition, the paper determines some calculations to estimate traffic congestion and energy con-sumption. Several alternative model designs are investigated. The model is evaluated using different multi-hop communication scenarios, and we compare the data rate and energy to provide an energy-efficient and low-cost leak detection system. © 2022 by the authors. Licensee MDPI, Basel, Switzerland.
A72: R071 | B72: S1 | C72: A Self-Healing Mesh Network without Global-Time Synchronization | D72: 2024 | E72: Conference paper | F72: Sahin, A.; Arslan, H. | G72: IEEE International Conference on Communications | H72: 10.1109/icc51166.2024.10622330 | I72: Include | K72: 2.1 | L72: PROTO | M72: Low | O72: =IF(N72="",IF(I72="Include","Include",J72),N72) -> Include | P72: In this paper, we propose a slot-based protocol that does not rely on global-time synchronization to achieve a self- healing mesh network. With the proposed protocol, each node synchronizes with its neighbors locally by adjusting its time to transmit based on the reception instant of a decoded beacon signal. Also, it determines its slots without any coordinator to avoid collisions. Finally, to communicate the messages over the mesh network, it identifies the forwarding nodes on the shortest path without knowing the entire communication graph. We show that the proposed protocol can effectively resolve collisions over time while enabling nodes to synchronize with each other in a distributed manner. We numerically analyze the performance of the proposed protocol for different configurations under a realistic channel model considering asymmetrical links. We also implement the proposed method in practice with Long-Range (LoRa) devices. We demonstrate that the nodes adapt themselves to changes in the network and deliver a message from a sensing node to a reference node via multi-hop routing. © 2024 IEEE.
A73: R072 | B73: S1, S2 | C73: PiTFiT: Payload-Level Bit-Flip Attacks on Stateless IoT Broadcasting Protocols | D73: 2025 | E73: Conference paper | F73: Ahmed, S.T.; Nadella, Y.S.; Kulkarni, A.R.; Annamalai, A.; Chouikha, M. | G73: Proceedings of the IEEE National Aerospace Electronics Conference, NAECON | H73: 10.1109/naecon65708.2025.11235480 | I73: Include | K73: 2.1 / 2.2 | L73: SEC | M73: High | O73: =IF(N73="",IF(I73="Include","Include",J73),N73) -> Include | P73: Stateless broadcasting protocols in IoT networks are vulnerable to payload-level bit-flipping attacks. We present two attack schemes: physical-layer corruption detected by CRC and network-layer corruption that bypasses CRC. Using a LoRa mesh testbed, we show how a compromised node silently propagates false data, revealing critical vulnerabilities and motivating lightweight integrity defenses. © 2025 IEEE.
A74: R073 | B74: S1 | C74: Introducing Smart Water Meters in Bangladesh: Enhancing AI-Based Water Distribution, Control and Optimization | D74: 2025 | E74: Conference paper | F74: Mahin, Md.I.S.; Arefin, Md.S.; Bepary, R. | G74: 2025 28th International Conference on Computer and Information Technology, ICCIT 2025 | H74: 10.1109/iccit68739.2025.11491671 | I74: Exclude | J74: EC7 | O74: =IF(N74="",IF(I74="Include","Include",J74),N74) -> EC7 | P74: Bangladesh's water utilities face severe challenges from outdated analog metering, including high water losses, revenue shortfalls, and inequitable distribution. This paper presents a smart water-metering system that leverages Internet of Things (IoT) sensors and artificial intelligence to modernize water-distribution management. The proposed solution enables real-time monitoring of water usage and quality via IoT-enabled flow and water-quality sensors, delivering instantaneous data to utilities and consumers. A machine learning anomaly detection module (Isolation Forest) identifies leaks, pipe bursts, and unauthorized consumption by flagging outlier usage patterns. To ensure reliable communication under diverse infrastructural conditions, the system supports multi-mode data transmission Wi-Fi, GSM cellular, LoRa long-range radio, Bluetooth mesh relay, and Ethernet. A smart billing platform with web and mobile interfaces automates meter reading, billing, and payment through digital wallets, improving transparency and convenience. The hardware is engineered for uninterrupted operation during loadshedding and power outages using a battery backup design. We evaluate monitoring accuracy, anomaly detection performance, and communication reliability; results demonstrate effective realtime usage tracking, timely leak/theft detection, and improved billing efficiency. © 2025 IEEE.
A75: R074 | B75: S1 | C75: Enhancing energy efficiency and QoS in Q-learning-based small-world WSNs | D75: 2026 | E75: Journal article | F75: Zhao, Y.; Huang, L.; Ren, M.; Shi, H. | G75: Ad Hoc Networks | H75: 10.1016/j.adhoc.2025.104123 | I75: Exclude | J75: EC6 | O75: =IF(N75="",IF(I75="Include","Include",J75),N75) -> EC6 | P75: In a wireless sensor network (WSN), achieving efficient data transmission while extending network lifetime remains a critical issue. Sensor nodes may fail due to energy depletion during mass data transmission, which results in frequent changes in the network topology. The frequent topology changes not only increase the complexity of network management and maintenance, but also severely impair both energy efficiency and quality-of-service (QoS). To address these challenges, in this paper, we construct a small-world WSN (SW-WSN) and address its joint optimization problem of energy efficiency and QoS. In the constructed SW-WSN, long-range (LoRa) links are used to replace some of the conventional links between sensor nodes as well as between nodes and the gateway, and a small-world model is introduced to reduce the intermediate hop count for data transmission. A Q-learning-based adaptive link allocation algorithm is proposed to map all conventional and LoRa links to state space and action space respectively and learn to form state–action pairs through training, which determines an optimal link replacement strategy under different network states and ultimately constructs a self-optimizing network architecture SW-WSN. Then, considering the network topology, link capacity, delay tolerance, and node energy of SW-WSN, the joint optimization problem of energy efficiency and QoS is formulated as an instance of linear programming (LP) with the objective of maximizing energy efficiency while ensuring QoS, and a heuristic algorithm is further designed to obtain the optimal solution. As shown by the simulation results, the Q-learning-based SW-WSN exhibits excellent learning capability and convergence stability across different network scales, successfully achieving a relatively ideal balance between energy efficiency and QoS. The Q-learning-based SW-WSN demonstrates substantial improvements in both energy efficiency (alive or dead devices, and network residual energy) and QoS (average transmission delay, data throughput, and bandwidth utilization) compared with the reinforcement learning (RL)-based routing, low-energy adaptive clustering hierarchy (LEACH), conventional small-world characteristics (SWC), multihop data transmission, and direct data transmission methods. © 2025 Elsevier B.V. All rights are reserved, including those for text and data mining, AI training, and similar technologies.
A76: R075 | B76: S1 | C76: Multi-hop communication protocol for LoRa with software-defined networking extension | D76: 2021 | E76: Journal article | F76: Farooq, M.O. | G76: Internet of Things (Netherlands) | H76: 10.1016/j.iot.2021.100379 | I76: Include | K76: 2.1 | L76: PROTO | M76: Medium | O76: =IF(N76="",IF(I76="Include","Include",J76),N76) -> Include | P76: Long Range (LoRa) is a leading low-power wide-area networking technology, and LoRaWAN is the open MAC layer specification for LoRa technology. LoRaWAN operates in a star network topology, thus LoRaWAN forms single-hop network. LoRa technology allows customization of its PHY layer transmission parameters, such as bandwidth, spreading factor, transmission power, and coding rate, therefore long coverage can be achieved by using a lower bandwidth. However, a single-hop LoRaWAN network cannot achieve high data rate and long coverage simultaneous. To simultaneously achieve high data rate and long coverage, the LoRa PHY layer setting that yields the fastest data rate can be used, however it reduces coverage. To makeup for the reduced coverage multi-hop communication can be used. To enable multi-hop communication here a routing protocol for LoRa-based networks is presented. Moreover, to enable traffic engineering in LoRa-based networks, such as traffic load balancing a software-defined networking (SDN) extension for the protocol is also presented. Performance evaluation has shown that the proposed protocol and its SDN-based extension can match the coverage of LoRa PHY layer setting that offers maximum coverage at a relatively very high data rate and lower energy consumption. The protocol demonstrates up to 5 times higher packet reception ratio, and 63% lower energy consumption compared to the LoRa PHY layer setting that offers maximum coverage and reliability. Moreover, the protocols also outperform an existing state-of-the-are routing protocol for low-power wireless networks. © 2021 Elsevier B.V.
A77: R076 | B77: S1 | C77: New Field Server Addition Method for Low-Price Rice Cultivation Management System | D77: 2020 | E77: Conference paper | F77: Ishii, S.; Tatsumi, S.; Tanaka, M.S.; Okumura, Y.; Kochi, T. | G77: 2020 2nd International Conference on Computer Communication and the Internet, ICCCI 2020 | H77: 10.1109/iccci49374.2020.9145992 | I77: Exclude | J77: EC7 | O77: =IF(N77="",IF(I77="Include","Include",J77),N77) -> EC7 | P77: We are developing a rice cultivation management systems using a field server to reduce the workload of farmers. The feature of our field server is a reasonable price. In order to achieve the reasonable price, the accuracy of time synchronization is sacrificed. At present, it is possible to manage environmental data for crops and fields using sensors. However, there are some points to be improved in the current field server. The first is transmission scheduling in advance is had to set up. The second is that field servers cannot be added during the operation. This paper describes a method to notify all nodes of additional field server information and scheduling to solve the above problem. Simultaneous transmission type flooding method is described in detail. We will also report the experimental results. This protocol is robust for the rice cultivation management systems because the field server is stable. Therefore, it meets farmers' expectation to utilize a reasonable field server. © 2020 IEEE.
A78: R077 | B78: S1 | C78: Efficient energy management for IoT applications in smart mesh networks for hybrid renewable generation | D78: 2026 | E78: Book Chapter | F78: Ngo, T.D.; Pham, V.K.; Ferrero, F.; Le Thanh, N. | G78: Hybrid Energy Systems: Planning, operation and optimization | I78: Exclude | J78: EC7 | O78: =IF(N78="",IF(I78="Include","Include",J78),N78) -> EC7 | P78: This chapter introduces an innovative Internet of Things (IoT) system designed for efficient energy management in smart mesh networks, leveraging hybrid renewable energy sources for environmental monitoring. The proposed system, an energy-efficient solution for WSNs using LoRa Mesh technology integrated with the Ad-hoc On-Demand Distance Vector (AODV) routing algorithm, addresses the challenges of energy consumption and connectivity in remote areas with unstable power supplies and harsh conditions. Using solar power supplemented by battery backup, the system ensures reliable data transmission while minimizing energy consumption during severe weather, with devices capable of functioning for up to a month solely on battery backup. Field experiments in Vietnam highlight its effectiveness, showcasing improved energy efficiency and extended operational range, and demonstrate that the proposed system achieves a packet delivery success rate (DSR) of 95%–99%, reduces packet loss to 1%–5%. The solution not only enhances reliability in remote areas without 3G/4G coverage but also supports sustainable IoT applications in hybrid renewable energy systems. Copyright © The Institution of Engineering and Technology and its licensors 2026 First published 2025.
A79: R078 | B79: S1 | C79: Design and implementation of discharge monitoring system of parallel gap device based on LoRa technology | D79: 2020 | E79: Conference paper | F79: Yu, K.; Fang, Y.; Wang, Z.; Bai, B.; Xu, Y.; Ma, Z. | G79: 2020 IEEE 4th Conference on Energy Internet and Energy System Integration: Connecting the Grids Towards a Low-Carbon High-Efficiency Energy System, EI2 2020 | H79: 10.1109/ei250167.2020.9347316 | I79: Exclude | J79: EC7 | O79: =IF(N79="",IF(I79="Include","Include",J79),N79) -> EC7 | P79: In view of the fact that the current online monitoring device for lightning arresters cannot effectively monitor and judge the shortcomings of subsequent power frequency current technologies and the influencing factors such as communication blind zone in special environments such as remote mountain areas, a parallel gap discharge monitoring system based on LoRa technology is proposed. The system is based on the MSP430 or STM32 microcontroller and it is made up of two types of sensor node devices (master node device and child node device) and background receiving and processing platform. The system deploys the corresponding sensor node devices on the spot to realize the monitoring and transmission of the sensor data. The mesh network topology is used to carry out the relay transmission of the monitoring data in the ad hoc network and upload it to the corresponding background for analysis and processing. The system provides the data for quickly finding out the position of the action pole and tower of the parallel clearance device and the time of flashover. © 2020 IEEE.
A80: R079 | B80: S1 | C80: Multihop gateway-to-gateway communication protocol for lora networks | D80: 2019 | E80: Conference paper | F80: Dwijaksara, M.H.; Sook Jeon, W.; Jeong, D.G. | G80: Proceedings of the IEEE International Conference on Industrial Technology | H80: 10.1109/icit.2019.8755136 | I80: Include | K80: 2.1 | L80: RELAY | M80: Low | O80: =IF(N80="",IF(I80="Include","Include",J80),N80) -> Include | P80: The long range wide area network (LoRaWAN) forms a star topology where end device (ED) sends data to network server (NS) through gateway (GW). It requires a GW to be connected to the NS through an IP network as the backhaul link. However, when a LoRaWAN is deployed in a remote area, such connection may not be possible. Thus, it is important that the GW can reach the NS through multihop GW-to-GW (G2G) communication using LoRa technology. To realize it, we propose a multihop G2G communication protocol for LoRa networks. The proposed protocol includes both routing protocol and channel access scheme. A packet aggregation feature is also added for improving the transmission efficiency of GW. The simulation results demonstrate that the proposed protocol successfully enables multihop G2G communication for LoRa networks with reasonably good performance. © 2019 IEEE.
A81: R080 | B81: S1 | C81: Energy aware and quality of service routing mechanism for hybrid internet of things network | D81: 2021 | E81: Journal article | F81: Diratie, E.D.; Sharma, D.P.; Al Agha, K. | G81: Computers | H81: 10.3390/computers10080093 | I81: Exclude | J81: EC6 | O81: =IF(N81="",IF(I81="Include","Include",J81),N81) -> EC6 | P81: Wireless Multimedia Sensor Networks (WMSNs) based on IEEE 802.11 mesh networks are effective and suitable solutions for video surveillance systems in detecting intrusions in selected monitored areas. The IEEE 802.11-based WMSNs offer high bit rate video transmissions but are challenged by energy inefficiency issues and concerns. To resolve the energy inefficiency challenges, the salient research studies proposed a hybrid architecture. This newly evolved architecture is based on the integration of IEEE 802.11-based mesh WMSNs along with the LoRa network to form an autonomous and high bitrate, energy-efficient video surveillance system. This paper proposes an energy-aware and Quality of Service (QoS) routing mechanism for mesh-connected visual sensor nodes in a hybrid Internet of Things (IoT) network. The routing algorithm allows routing a set of video streams with guaranteed bandwidth and limited delay using as few visual sensor nodes as possible in the network. The remaining idle visual sensor nodes can be turned off completely, and thus it can significantly minimize the overall energy consumption of the network. The proposed algorithm is numerically simulated, and the results show that the proposed approach can help in saving a significant amount of energy consumption while guaranteeing bandwidth and limited delay. © 2021 by the authors. Licensee MDPI, Basel, Switzerland.
A82: R081 | B82: S1 | C82: Enhancing Quality-of-Service in LoRa Low-Power Wide-Area Networks via Multi-Hop Optimized Radio Resource Management | D82: 2024 | E82: Conference paper | F82: Jasim Alzubaidi, L.H.; Sunil, G.; Praveena, H.D.; Sathishkumar, N.; Manjula, B.M. | G82: 2nd International Conference on Integrated Circuits and Communication Systems, ICICACS 2024 | H82: 10.1109/icicacs60521.2024.10498522 | I82: Include | K82: 2.1 | L82: PROTO | M82: Low | O82: =IF(N82="",IF(I82="Include","Include",J82),N82) -> Include | P82: In transport systems in particular, LoRa wireless communication has become an essential technology for intelligent critical infrastructures. Optimizing transmission policy parameters, including carrier frequency, bandwidth, coding rate, and spreading factor, is crucial for achieving excellent Quality of Service (QoS) for LoRa systems; however, current methods have not fully optimized all LoRa parameters. In order to efficiently share information, the proposed Multiobjective Q Learning based LoRa (MQ-LoRa) uses a hybrid topology consisting of a cluster root rotating tree, wherein IoT nodes adhere to a cluster topology inspired by cellular tissues, while gateways follow a tree topology. For cluster construction, a membrane-inspired clustering algorithm is created, and influence scores are used to determine which header node is best. The study presents Data QoS Ranking for IoT nodes, which uses the new LoRa frame structure field QoS Ranking (QRank) to classify data into priority and non-priority categories. The Soft Actor Critic (SAC) fast deep reinforcement learning model is used for optimal transmission policy enforcement, taking into account signal-to-interference-plus-noise ratio, QRank, and other environmental characteristics. After that, the transmission policy is optimized taking carrier frequency, bandwidth, coding rate, and spreading factor into account. Furthermore, a multi-hop routing method with concurrent optimization that uses shuffling shepherd and mayfly optimization rates routes according to fitness standards. A multi-weighted sum approach is used to establish a weighted duty cycle in LoRa IoT networks to minimize resource inefficiency and loss of information. Using the NS3.26 LoRaWAN module, performance evaluation measures energy consumption, latency, throughput, packet receipt ratio, and packet rejection ratio, among other parameters. Comparison with popular LoRa techniques shows that the suggested MQ-LoRa performs better energy consumption of 56 mJ than exisitng Reinforcement Learning based LoRA, according to experimental results. © 2024 IEEE.
A83: R082 | B83: S1 | C83: Dissemination and Multi-hop Dissemination Based-on LoRaWAN for Emergency Communication in Low Traffic Vehicular Ad Hoc Networks | D83: 2022 | E83: Conference paper | F83: Harshavardhan Reddy, B.; Gunasekaran, M. | G83: Proceedings of 3rd International Conference on Intelligent Engineering and Management, ICIEM 2022 | H83: 10.1109/iciem54221.2022.9853130 | I83: Exclude | J83: EC6 | O83: =IF(N83="",IF(I83="Include","Include",J83),N83) -> EC6 | P83: To improve the Packet delivery ratio (PDR) in vehicular Ad Hoc network based on LoRaWAN using cluster-based multi-hop dissemination technique with location information and clustering in low traffic. Materials and Methods: Clustering of nodes with location aid in Vehicular Ad hoc Network is proposed to improve the PDR in low traffic scenarios. Based on the proximity of the nodes from the current node, nodes are clustered and a cluster head is selected for transmission which improves the reliability of the system. This research adopts a novel location aided routing approach of location aided routing for efficient communication. Sample size determined is 22 with actual power of 0.9642. Results: It is observed that proposed cluster-based multi-hop dissemination is 0.36% better when compared to conventional multi-hop dissemination in low traffic in terms of PDR. The statistical significance of two techniques observed is P < 0.001 in the independent sample T test. Conclusion: Results have confirmed that the proposed Cluster-based multi-hop dissemination in location aided vehicular ad hoc network based on LoRaWAN doesn't show significance greater than 0.36% better PDR using the location information and clustering of nodes in low traffic. © 2022 IEEE.
A84: R083 | B84: S1 | C84: Adapting LoRaWAN Relay Specification for Battery-Sustainable Subterranean LoRa Mesh Networks | D84: 2026 | E84: Conference paper | F84: Udugampola, N.; Ai, X.; Li, B.; Gong, H.; Seneviratne, A. | G84: Proceedings - International Conference on Computer Communications and Networks, ICCCN | H84: 10.1109/icccn69946.2026.11662683 | I84: Include | K84: 2.1 | L84: RELAY | M84: Medium | O84: =IF(N84="",IF(I84="Include","Include",J84),N84) -> Include | P84: Traditional IoT technologies such as LoRaWAN, Sigfox, and NB-IoT rely on single-hop star topologies, requiring many gateways to cover large areas. In subterranean environments where cellular coverage and grid power may be unavailable, such deployments are often impractical. This paper presents a novel LoRa mesh network designed for such environments, capable of operating for years on battery power. While the recent LoRaWAN relay specification supports two-hop communication via an intermediate relay between an end device and a gateway, our work is the first to extend this specification for on-demand multi-hop communication across multiple LoRa repeaters, adapting its sleep mechanism. Our proposed sleep mechanism combines an on-demand cascaded repeater wakeup process with a repeater synchronization strategy, minimizing the power consumption. Moreover, our network architecture integrates existing packet routing and collision recovery mechanisms and is highly scalable and general-purpose, enabling a wide range of applications. Network simulations demonstrate that the proposed design operates reliably, sustaining years on battery power, while the repeater synchronization strategy further reduces average energy consumption by up to 50%. [Code: https://bit.ly/4nALuNX] © 2026 IEEE.
A85: R084 | B85: S1 | C85: Rapid and Resilient LoRa Leap: A Novel Multi-Hop Architecture for Decentralised Earthquake Early Warning Systems | D85: 2024 | E85: Journal article | F85: Ranasinghe, V.; Udara, N.; Mathotaarachchi, M.; Thenuwara, T.; Dias, D.; Prasanna, R.; Edirisinghe, S.; Gayan, S.; Holde… | G85: Sensors | H85: 10.3390/s24185960 | I85: Include | K85: 2.1 | L85: PROTO | M85: Medium | O85: =IF(N85="",IF(I85="Include","Include",J85),N85) -> Include | P85: We introduce a novel LoRa-based multi-hop communication architecture as an alternative to the public internet for earthquake early warning (EEW). We examine its effectiveness in generating a meaningful warning window for the New Zealand-based decentralised EEW sensor network implemented by the CRISiSLab operating with the adapted Propagation of Local Undamped Motion (PLUM)-based earthquake detection and node-level data processing. LoRa, popular for low-power, long-range applications, has the disadvantage of long transmission time for time-critical tasks like EEW. Our network overcomes this limitation by broadcasting EEWs via multiple short hops with a low spreading factor (SF). The network includes end nodes that generate warnings and relay nodes that broadcast them. Benchmarking with simulations against CRISiSLab’s EEW system performance with internet connectivity shows that an SF of 8 can disseminate warnings across all the sensors in a 30 km urban area within 2.4 s. This approach is also resilient, with the availability of multiple routes for a message to travel. Our LoRa-based system achieves a 1–6 s warning window, slightly behind the 1.5–6.75 s of the internet-based performance of CRISiSLab’s system. Nevertheless, our novel network is effective for timely mental preparation, simple protective actions, and automation. Experiments with Lilygo LoRa32 prototype devices are presented as a practical demonstration. © 2024 by the authors.
A86: R085 | B86: S1 | C86: A Study of Scalable Mesh Algorithms for Large-scale Aquaculture using LoRa | D86: 2024 | E86: Conference paper | F86: Hern Ryan, S.Y.; Xiang, L.J.; Su Wee, E.T.; Yiang, L.K.; Qiao Yu, S.L.; Abbas, M.F.B. | G86: 2024 IEEE VTS Asia Pacific Wireless Communications Symposium, APWCS 2024 | H86: 10.1109/apwcs61586.2024.10679328 | I86: Include | K86: 2.1 | L86: PROTO | M86: Low | O86: =IF(N86="",IF(I86="Include","Include",J86),N86) -> Include | P86: COVID-19 significantly impacted the fishing industries, affecting fish supply, demand, distribution, labour and production. The aquaculture industry needs to monitor water quality manually, which is time-consuming and costly. This paper explores mesh algorithms such as DSDV (Destination Sequenced Distance Vector) and AODV (Ad-hoc On-Demand Distance Vector Routing) on IoT for remote monitoring of aquaculture farms. Comparisons of routing algorithms analysis were made regarding reliability and power consumption. The AODV mesh algorithm on LoRa has demonstrated better network efficiencies and lower power capabilities for long-range data gathering across large areas during daily operations. © 2024 IEEE.
A87: R086 | B87: S1, S2 | C87: NETRA: A Decentralized LoRa-MANET Ecosystem for AI-Driven Collaborative Reconnaissance in GPS-Denied Environments | D87: 2026 | E87: Conference paper | F87: Sinkar, A.; Shetty, V.; Shinde, A. | G87: 17th International Conference on Advances in Computing, Control, and Telecommunication Technologies, ACT 2026 | I87: Exclude | J87: EC7 | O87: =IF(N87="",IF(I87="Include","Include",J87),N87) -> EC7 | P87: Modern military operations frequently encounter communication blackouts and GNSS-denied environments caused by electronic warfare and infrastructure destruction. This paper proposes NETRA (Networked Emergency Tactical Radio Awareness), an integrated helmet-mounted ecosystem designed for resilient indigenous soldier-level situational awareness. NETRA acts as a fallback communication system. The system fuses three core capabilities. First, a Hybrid Positioning Subsystem combining GPS for macro-localization and Ultra-Wideband (UWB) for less than 30 cm intra-squad relative tracking in jammed environments. Second, an Edge-AI Reconnaissance engine utilizing quantized YOLO-based models on ESP32 hardware to detect human, weapon, and tank threats with less than 1 second latency. Third, an Encrypted LoRa-based Mobile Ad Hoc Network (MANET) for multi-hop tactical data relay. By transmitting 16-byte metadata packets instead of raw video, NETRA bypasses LoRa’s bandwidth constraints while maintaining end-to-end AES-128 security. Experimental prototyping demonstrates a 1 km Non-Line-of-Sight (NLOS) range, 8.7 km Line-of-Sight (LOS) range, and an energy-aware operational endurance of 13.3 hours. This architecture establishes a persistent shared knowledge bank, delivering critical intelligence via an eyes-free, in-ear audio interface to enhance decision-making in infrastructure-denied tactical theaters. © Grenze Scientific Society, 2026.
A88: R087 | B88: S1 | C88: IoT multi-hop facilities via LORA modulation and LORAWAN protocol within thin linear networks | D88: 2021 | E88: Conference paper | F88: Basili, F.; Parrino, S.; Peruzzi, G.; Pozzebon, A. | G88: 2021 IEEE Sensors Applications Symposium, SAS 2021 - Proceedings | H88: 10.1109/sas51076.2021.9530117 | I88: Include | K88: 2.1 | L88: RELAY | M88: Low | O88: =IF(N88="",IF(I88="Include","Include",J88),N88) -> Include | P88: This paper proposes a novel network architecture integrating a multi-hop Long Range (LoRa)-based thin linear network within a LoRa Wide Area Network (LoRaWAN) infrastructure, with the aim of proposing linear distributed measurement systems forwarding their collected data to a LoRaWAN server by means of a hybrid LoRa-LoRaWAN node. Such device is able to collect LoRa packets coming from the linear network and to encapsulate them in LoRaWAN packets transmitted to the remote server by means of standard LoRaWAN Gateways. The operation of the nodes is regulated by an ad-hoc routing protocol which aims at minimizing their active period, in order to reduce their power consumption increasing the overall system lifetime. Similarly, the synchronization of the nodes aims at increasing the robustness of the network reducing at minimum packet losses. The effectiveness of the proposed network architecture in terms of successful packet deliveries and reduction of active time is tested in different configurations, exploiting 2-node, 3-node and 4-node chains as well as adopting increasingly larger cycle periods. Results show that the proposed configuration ensures a noteworthy robustness in terms of packets delivery while maintaining the duty-cycling at levels that may guarantee long life times and autonomous operation to the overall infrastructure. © 2021 IEEE.
A89: R088 | B89: S1, S2 | C89: Multi-Hop and Mesh for LoRa Networks: Recent Advancements, Issues, and Recommended Applications | D89: 2024 | E89: Journal article | F89: Wong, A.W.-L.; Goh, S.L.; Hasan, M.K.; Fattah, S. | G89: ACM Computing Surveys | H89: 10.1145/3638241 | I89: Include | K89: 2.1 | L89: SURVEY | M89: High | O89: =IF(N89="",IF(I89="Include","Include",J89),N89) -> Include | P89: A comprehensive review is presented on the latest approaches to solutions focusing on multi-hop and mesh LoRa networks through the evaluation of simulations and real-world experiments, based on papers published between 2015 and 2023. The approaches are systematically classified into four (4) aspects: energy awareness, concurrent access and duty cycle regulations, routing protocols, and security. The first aspect encompasses parameter selection, distance, and clustering. The second aspect focuses on network segregation and time synchronisation. The third aspect covers proactive, reactive, and hybrid routing protocols. The aspect of security includes privacy and Denial-of-Service (DoS). Findings show a consensus that multi-hop networks and adherence to radio duty cycle are able to lower average power consumption. Concurrent access method can improve network performance, but more research is needed due to different conclusions. Reactive protocols have a slight advantage over proactive protocols in terms of node deployment scalability and lower power consumption due to less frequent routing table updates. Hybrid protocols are only beneficial in specific topology deployments. Security is still a major concern for LoRa networks, particularly on attacks such as Man-In-The-Middle (MITM), spoofing, wormholes, flooding, packet replay, and information disclosure. The upcoming trend of implementing machine learning algorithms to multi-hop and mesh LoRa networks opens up a wide range of possibilities, ranging from airspace efficiency, efficient route selection, and improving data throughput. A detailed discussion of the aspects' issues and recommended industry applications that will benefit from multi-hop and mesh LoRa networks are also provided. © 2024 Copyright held by the owner/author(s). Publication rights licensed to ACM.
A90: R089 | B90: S1 | C90: A Routing Protocol for LoRA Mesh Networks | D90: 2018 | E90: Conference paper | F90: Lundell, D.; Hedberg, A.; Nyberg, C.; Fitzgerald, E. | G90: 19th IEEE International Symposium on a World of Wireless, Mobile and Multimedia Networks, WoWMoM 2018 | H90: 10.1109/wowmom.2018.8449743 | I90: Include | K90: 2.1 | L90: PROTO | M90: High | O90: =IF(N90="",IF(I90="Include","Include",J90),N90) -> Include | P90: A limitation of current LoRa networks is their single-hop nature. This causes difficulties in areas with poor Internet access, such as remote rural areas, or challenging radio environments, for example in metropolitan areas, as the LoRa gateway must be placed at a location with backhaul access to the network server, but must nonetheless be reachable by all end devices. To facilitate these applications, we present a new routing protocol to enable mesh networking with LoRa, allowing for multihop networking between gateways to extend coverage. Our protocol is tailored specifically to the requirements of LoRa networks. We have developed a proof-of-concept implementation of the protocol and have shown its effectiveness in both laboratory tests and a field trial in a real-world LoRa deployment. © 2018 IEEE.
A91: R090 | B91: S1, S2 | C91: A Robust Multi-Hop LoRa-Based Emergency Communication System for Maritime Safety | D91: 2025 | E91: Conference paper | F91: Koppaka, A.; Valsan, V. | G91: 2025 Control Instrumentation System Conference, CISCON 2025 | H91: 10.1109/ciscon66933.2025.11337728 | I91: Exclude | J91: EC7 | O91: =IF(N91="",IF(I91="Include","Include",J91),N91) -> EC7 | P91: Maritime safety is a major concern for fishermen who operate near international borders, as unintentional crossings can lead to legal consequences and security risks. Present systems that utilise GSM-based tracking and LoRa WAN networks are significantly limited in deep-sea environments due to their low coverage and their dependence on centralised gateways. We propose a LoRa-based multi-hop mesh networking system that offers fishermen emergency distress signalling and real-time border notifications in order to overcome these difficulties. In order to combine power efficiency with prompt emergency response, the system incorporates GPS-based geofencing with a Point-in-Polygon (PIP) method, a 2-kilometer safety zone for early warning notifications, and an adaptive transmission mechanism. Our proposed LoRa mesh network uses multi-hop relaying to extend communication up to 140 kilometres in real-world marine environments, in contrast to standard LoRa WAN, which has a very restricted range. Experimental evaluations show that our approach greatly increases reliability and range, ensuring distress messages reach the coast. The proposed prototype model lowers socioeconomic risks, improves safety monitoring, and offers a long-lasting, reasonably priced marine security system by proactively avoiding unintentional crossings, thereby enhancing United Nations Sustainable Development Goals 9 and 11. © 2025 IEEE.
A92: R091 | B92: S1 | C92: A Distributed Drone Weather System using LoRaWAN and LoRa Meshnet | D92: 2025 | E92: Conference paper | F92: Kim, H.; Pyo, J.; Park, J.; Park, J.; Wu, J.; Smith, A.H. | G92: Proceedings - 2025 International Conference on Robotic Computing and Communication, RoboticCC 2025 | H92: 10.1109/roboticcc68732.2025.00020 | I92: Exclude | J92: EC7 | O92: =IF(N92="",IF(I92="Include","Include",J92),N92) -> EC7 | P92: Traditional weather monitoring infrastructure struggles to provide continuous, high-resolution data in remote rural areas and disaster zones where communication networks are sparse or overloaded. This paper presents a distributed drone-based weather observation system that uses LoRaWAN communication and an integrated LoRa mesh network to extend coverage and resilience. Each autonomous drone in the system is equipped with weather sensors (temperature, humidity, wind, air quality, GPS) and communicates over long-range, low-power LoRa links, enabling wide-area data collection independent of cellular networks. A key contribution is a custom peer-to-peer mesh networking algorithm that allows drones to relay and aggregate sensor data among themselves, so that only one drone needs a direct LoRaWAN gateway connection for the entire fleet. This approach eliminates single points of failure and balances energy use across drones, ensuring the network remains operational even if individual units go offline. We implemented a prototype with off-the-shelf hardware and demonstrated end-to-end connectivity through a LoRaWAN gateway to a cloud database, confirming reliable real-time data delivery over several kilometers. The proposed system is cost-effective, rapidly deploy-able, and scalable, making it well-suited for social applications such as rural agriculture monitoring, wildfire and flood response, and any scenario where timely local weather information is critical but conventional infrastructure is unavailable. ©2025 IEEE.
A93: R092 | B93: S1 | C93: Extending data transmission in the multi-hop LoRa network | D93: 2022 | E93: Journal article | F93: Kim, J.; Jenkins, J.; Seol, J.; Kwak, M. | G93: Issues in Information Systems | H93: 10.48009/3_iis_2022_124 | I93: Include | K93: 2.1 | L93: PROTO | M93: Low | O93: =IF(N93="",IF(I93="Include","Include",J93),N93) -> Include | P93: In recent years, with the widely available broadband network connectivity and sensing technology, the Internet of Things (IoT) provides a variety of smart services in both urban and rural environments. For example, sensing devices placed in the community not only provide environmental monitoring, but also are used to inform the public about rapidly changing real-time events. The data collected from sensors will help the community improve quality of life of citizens, and can be used for the city development. It has been known that LoRa (Long Range), a notable LPWAN (Low Power Wide Area Network) wireless communication technology, is suitable for providing IoT service with the help of wide coverage, long battery lifetime and low cost to deploy and operate. However, as the application of IoT is becoming increasingly complex, simple sensor data does not satisfy user requirements, and the demand for a variety of multimedia data transmission is increasing. Specifically, many applications require large image data transmission for improved service. A network based on LoRa supports data communication at up to 10 km range with the minimum data rate, and LoRaWAN is operated with a Star-of-Stars topology. However, due to the narrow bandwidth of LoRa, it takes a great deal amount of time to transmit large image files. A possible solution is to reduce distance between sensing devices and a gateway by deploying more gateways and maximize the data rate. However, as expected, particularly in case of monitoring rural environments such as farms, forests, mountains, etc., it is costly to provide the required power and network connectivity for the deployment of additional gateways. As a solution to two challenges, large image transmission and service coverage extension, multi-hop LoRa network is introduced. In this study, we implemented and tested a multi-hop LoRa network. In the experiment, we were able to transmit an image file through multiple end devices successfully. © 2023 Issues in Information Systems. All rights reserved.
A94: R093 | B94: S1 | C94: Long-Range wide-area network for secure network connections with increased sensitivity and coverage | D94: 2022 | E94: Conference paper | F94: Kiran, S.; Gupta, G. | G94: AIP Conference Proceedings | H94: 10.1063/5.0082116 | I94: Exclude | J94: EC1 | O94: =IF(N94="",IF(I94="Include","Include",J94),N94) -> EC1 | P94: Long Range Wide Area Network (LoRaWAN) is one of the most common broad-band low-power networks that use Semtech's patented LoRa modulation to provide high sensitivity for long-band rates at low data rates. LoRaWAN covers thousands of end-devices (sensors) that operate on batteries with single-hop gates. To communicate with the network server, every gateway needs an internet connection or a private network (Ethernet, WiFi, 3G/4G). Several gateways are needed to cover the final devices in obstructed areas with mountains, trees or simply vast areas. There could be some places where Internet/mobile coverage is lacking. This quickly generates Internet access costs in these areas unless a solution that routes messages between the gates through the current LoRa radio communications standard has been established. This reduces the internet connections available while providing coverage. In order that LoRaWAN devices with two-way capabilities should be supported according to regional regulations and that a road protocol should be provided that minimizes extra data that is provided with messages routing over a network. This solution was developed and evaluated. Triple gateway experiments showed that the solution offers a working routing protocol with a maximum routing time of 3 bytes. Though quick enough, end devices located farthest from the port of the server link will be bidirectionally supported. © 2022 Author(s).
A95: R094 | B95: S1 | C95: A Resilient LoRa-Based Solution to Support Pervasive Sensing | D95: 2023 | E95: Journal article | F95: Manzoni, P.; Merzougui, S.E.; Palazzi, C.E.; Pozzan, P. | G95: Electronics (Switzerland) | H95: 10.3390/electronics12132952 | I95: Include | K95: 2.1 | L95: PROTO | M95: Low | O95: =IF(N95="",IF(I95="Include","Include",J95),N95) -> Include | P95: Today, billions of small devices that can sense things are connected, creating the Internet of Things (IoT). This major technological step has led to ideas like smart cities, smart factories, and smart countries. One important use of this technology is pervasive sensing, which could benefit from a network that covers a wide area but does not use much power. This paper looks closely at the advantages and disadvantages of using LoRa—a network technology that can reach long distances with limited energy use—in situations like this. To this aim, we have created a holistic solution to manage the considered network enabling synchronization, routing, and reliability. In particular, we have even developed an adaptive spreading factor mechanism, simple and effective in allowing the network to cope better when the connection is not very good. © 2023 by the authors.
A96: R095 | B96: S1 | C96: CDR: Bandwidth-Efficient Cross-Interface Downlink Relay Scheme for Low-Power Multihop Wireless Networks | D96: 2024 | E96: Journal article | F96: Qin, H.; Chen, W.; Li, N.; Wang, T.; Deng, Y.; Yang, G.; Peng, Y. | G96: IEEE Internet of Things Journal | H96: 10.1109/jiot.2024.3350634 | I96: Exclude | J96: EC6 | O96: =IF(N96="",IF(I96="Include","Include",J96),N96) -> EC6 | P96: Driven by emerging wireless applications, numerous smart objects will be deployed, forming things networks interconnected by the Internet of Things (IoT). Many of these networks follow the low-power multihop wireless network (LPMWN) paradigm due to the good scalability of the distributed schemes adopted by LPMWNs. Although distributed schemes may operate satisfactorily most of the time, they are often complex and costly to manage. To simplify network management, the LoRa (long range) wireless technology has been introduced into LPMWNs for centralized network control. Unfortunately, due to LoRa's inherent limitation that a downlink packet must be in response to a precedent uplink packet, the existing protocols typically require every node to periodically send an uplink packet to the gateway for downlink network command dissemination. This causes intensive uplink collisions and quickly depletes LoRa bandwidth, especially when the network is large. In light of these pitfalls, we propose a (cross-interface downlink relay (CDR)) scheme, which leverages the ZigBee communications that are already available in LPMWNs to relay LoRa downlink data traffic for bandwidth-efficient and delay-guaranteed data dissemination. CDR determines the optimal network topology for bandwidth-minimized data relay while adjusting system parameters to ensure each node's delay requirement under network dynamics. A prototype system is implemented by integrating LoRa and ZigBee into an IoT platform. Extensive outdoor experiments show that the bandwidth consumption of CDR is 39.3% lower than a state-of-the-art LoRa data dissemination protocol for ZigBee-based LPMWNs under a moderate data traffic and delay requirement. Besides, CDR improves energy efficiency and network lifetime significantly. © 2014 IEEE.
A97: R096 | B97: S1 | C97: Wireless mesh networking: An IoT-oriented perspective survey on relevant technologies | D97: 2019 | E97: Journal article | F97: Cilfone, A.; Davoli, L.; Belli, L.; Ferrari, G. | G97: Future Internet | H97: 10.3390/fi11040099 | I97: Include | K97: 2.1 | L97: SURVEY | M97: Medium | O97: =IF(N97="",IF(I97="Include","Include",J97),N97) -> Include | P97: The Internet of Things (IoT), being a "network of networks", promises to allow billions of humans and machines to interact with each other. Owing to this rapid growth, the deployment of IoT-oriented networks based on mesh topologies is very attractive, thanks to their scalability and reliability (in the presence of failures). In this paper, we provide a comprehensive survey of the following relevant wireless technologies: IEEE 802.11, Bluetooth, IEEE 802.15.4-oriented, and Sub-GHz-based LoRa. Our goal is to highlight how various communication technologies may be suitable for mesh networking, either providing a native support or being adapted subsequently. Hence, we discuss how these wireless technologies, being either standard or proprietary, can adapt to IoT scenarios (e.g., smart cities and smart agriculture) in which the heterogeneity of the involved devices is a key feature. Finally, we provide reference use cases involving all the analyzed mesh-oriented technologies. © 2019 by the authors.
A98: R097 | B98: S1 | C98: Routing in LoRaWAN: Overview and Challenges | D98: 2020 | E98: Journal article | F98: Osorio, A.; Calle, M.; Soto, J.D.; Candelo-Becerra, J.E. | G98: IEEE Communications Magazine | H98: 10.1109/mcom.001.2000053 | I98: Include | K98: 2.1 | L98: SURVEY | M98: High | O98: =IF(N98="",IF(I98="Include","Include",J98),N98) -> Include | P98: LPWAN technologies are playing a major role in the IoT scenario due to their extensive radio range, use of free frequency bands, and low energy consumption. Among these technologies, longrange WAN (LoRaWAN) transmits through several kilometers with data rates up to 5.5 kb/s, making it useful for applications such as smart city monitoring, precision agriculture, and environmental tracking. However, LoRaWAN supports only one-hop communication between end nodes and gateways. Because links can be kilometers long, LoRaWAN signals may encounter obstacles or interference, affecting packet reception. Therefore, different studies have proposed using routing schemes to create multihop communication and improve LoRaWAN performance. The article has the following contributions: first, we present the main approaches to build multihop communication in LoRa networks. Second, we summarize different routing protocols proposed for the technology. Finally, we describe different challenges to improve the performance of routing protocols for LoRaWAN. © 1979-2012 IEEE.
A99: R098 | B99: S1 | C99: NeuroMesh: Decentralized Edge Mesh for Scalable IoT with Future LoRa and Autonomous Control Integration | D99: 2025 | E99: Conference paper | F99: Ramesh, K.; Durgaprasad, R.; Ashwin Varma, T.; Harish, S.; Jayapradha, A.; Kalaivani, K. | G99: 2025 IEEE 1st International Conference on Innovations in Engineering and Next-Generation Technologies for Sustainability, ICINVENTS 2025 | H99: 10.1109/icinvents64613.2025.11401504 | I99: Exclude | J99: EC6 | O99: =IF(N99="",IF(I99="Include","Include",J99),N99) -> EC6 | P99: The Internet of Things (IoT) ecosystem continues to expand rapidly across domains such as smart agriculture, environmental monitoring, and urban infrastructure. Despite its potential, conventional cloud-centric IoT architectures remain constrained by scalability, latency, and resilience limitations, particularly in rural or resource-constrained regions. This paper presents NeuroMesh, a decentralized edge mesh framework built upon ESP32 devices, incorporating optional LoRa overlays and a planned autonomous control layer. NeuroMesh leverages a WiFi mesh backbone for low-latency multi-hop communication and extends coverage with LoRa-based long-range links. Experimental evaluation using a 6-node laboratory deployment demonstrates high packet delivery ratios (PDR), predictable latency growth with hop count, and energy efficiency under duty-cycled operation. Furthermore, a roadmap is provided for integrating Multi-Agent Reinforcement Learning (MARL), enabling adaptive routing, load balancing, and energy-aware decisions at the edge. NeuroMesh thus offers a resilient and extensible foundation for next-generation distributed IoT networks. © 2025 IEEE.
A100: R099 | B100: S1 | C100: Practical Evaluation of Ranging Performance of 923 MHz LoRa with Meshtastic | D100: 2025 | E100: Conference paper | F100: Nakudom, C.; Kotpetch, H.; Khongdeach, T.; Jariyanorawiss, T.; Chongburee, W. | G100: Proceedings, International Conference on Electrical, Control and Instrumentation Engineering, ICECIE | H100: 10.1109/icecie66637.2025.11363862 | I100: Include | K100: 2.1 | L100: COMMUNITY | M100: High | O100: =IF(N100="",IF(I100="Include","Include",J100),N100) -> Include | P100: This paper presents an experimental investigation of the practical communication range of LoRa, a widely available long-range radio technology operating at 923 MHz, commonly used in IoT applications. LoRa typically uses a star topology, where the range is limited by the single-hop distance between a node and a gateway. To overcome this limitation, mesh networking solutions such as Meshtastic can extend coverage by relaying messages through intermediate nodes. The experiment was conducted on a university campus, representing a dense and realistic deployment environment. Antenna heights were set approximately at human level rather than mounted on towers, to reflect typical mobile or handheld usage scenarios. A range of LoRa parameters was tested to evaluate their impact on communication distance. Results indicate that ground-level, point-to-point LoRa communication with legally limited transmit power achieves a usable range of approximately 700 m. The range can be significantly extended using a mesh network configuration. © 2025 IEEE.
...

Sheet PRISMA
A1: IDENTIFICATION
A2: Records from Scopus S1 | B2: ='Search log'!G2 -> 219
A3: Records from Scopus S2 | B3: ='Search log'!G3 -> 103
A4: Records from Scopus S3b | B4: ='Search log'!G5 -> 212 | C4: S3 (1,156) replaced by S3b; see Search log
A5: Total records identified | B5: =SUM(B2:B4) -> 534
A6: Duplicate records removed | B6: =B5-COUNTA(Screening!$A$2:$A$510) -> 25 | C6: Same paper found by more than one string, or listed twice by Scopus
A7: SCREENING (title and abstract)
A8: Records screened | B8: =COUNTA(Screening!$A$2:$A$510) -> 509
A9: Records excluded | B9: =B8-B10 -> 261
A10: Records included for full-text assessment | B10: =COUNTIF(Screening!$O$2:$O$510,"Include") -> 248
A11: Excluded: EC1 single-hop LoRaWAN only | B11: =COUNTIF(Screening!$O$2:$O$510,"EC1") -> 5
A12: Excluded: EC2 physical layer only | B12: =COUNTIF(Screening!$O$2:$O$510,"EC2") -> 3
A13: Excluded: EC3 hardware above LoRa-node class | B13: =COUNTIF(Screening!$O$2:$O$510,"EC3") -> 1
A14: Excluded: EC4 not a full paper | B14: =COUNTIF(Screening!$O$2:$O$510,"EC4") -> 31
A15: Excluded: EC5 duplicate / earlier version | B15: =COUNTIF(Screening!$O$2:$O$510,"EC5") -> 3
A16: Excluded: EC6 off-topic | B16: =COUNTIF(Screening!$O$2:$O$510,"EC6") -> 164
A17: Excluded: EC7 application-focused | B17: =COUNTIF(Screening!$O$2:$O$510,"EC7") -> 51
A18: Excluded: EC8 not in English | B18: =COUNTIF(Screening!$O$2:$O$510,"EC8") -> 3
A19: Check: exclusion reasons add up (should be 0) | B19: =B9-SUM(B11:B18) -> 0
A20: Included, section 2.1 | B20: =COUNTIFS(Screening!$O$2:$O$510,"Include",Screening!$K$2:$K$510,"2.1") -> 148
A21: Included, section 2.1 / 2.2 (security) | B21: =COUNTIFS(Screening!$O$2:$O$510,"Include",Screening!$K$2:$K$510,"2.1 / 2.2") -> 11
A22: Included, section 2.3 | B22: =COUNTIFS(Screening!$O$2:$O$510,"Include",Screening!$K$2:$K$510,"2.3") -> 85
A23: Included, section 2.4 | B23: =COUNTIFS(Screening!$O$2:$O$510,"Include",Screening!$K$2:$K$510,"2.4") -> 4
A24: ELIGIBILITY (full text): fill in after reading
A25: Full texts assessed | C25: Number of included papers you read in full
A26: Full texts not retrievable | C26: Paywalled and not available via UT (count these separately)
A27: Full texts excluded, with reasons | C27: Total number excluded after reading; write the reasons in your PRISMA diagram
A28: Added via reference lists (snowballing) | C28: Papers found in reference lists of included papers
A29: Added from grey literature | C29: Meshtastic/MeshCore docs, datasheets, standards
A30: INCLUDED in the review | B30: =IF(B25="","",B25-B26-B27+B28+B29) | C30: Formula: assessed - not retrievable - excluded + snowballing + grey literature

Sheet Reading list
A1: Section | B1: ID | C1: Title | D1: Year | E1: Category | F1: DOI | G1: Why it matters (AI note, check when reading) | H1: Read? / full-text decision
A2: 2.1 | B2: R240 | C2: Enhancing Security and Trust in Internet of Things through Meshtastic Protocol Utilising Low-Range Technology | D2: 2024 | E2: COMMUNITY | F2: 10.3390/electronics13061055 | G2: Security and trust of the Meshtastic protocol; central for 2.1/2.2
A3: 2.1 | B3: R099 | C3: Practical Evaluation of Ranging Performance of 923 MHz LoRa with Meshtastic | D3: 2025 | E3: COMMUNITY | F3: 10.1109/icecie66637.2025.11363862 | G3: Meshtastic range measurements
A4: 2.1 | B4: R063 | C4: An Embedded Multi-Sensor IoT Platform for Agricultural Monitoring Using Meshtastic-Based LoRa Communication and Cloud Microservices | D4: 2026 | E4: COMMUNITY | F4: 10.3390/s26185839 | G4: Meshtastic used in a real deployment
A5: 2.1 | B5: R196 | C5: Communication and Energy Consumption Performance of a Multi-Floor Indoor Meshtastic-Based LoRa Mesh Network | D5: 2026 | E5: COMMUNITY | F5: 10.1049/cmu2.70221 | G5: Meshtastic multi-floor mesh: communication and energy
A6: 2.1 | B6: R138 | C6: Multi-Hop LoRa Networks Enabled by Concurrent Transmission | D6: 2017 | E6: FLOOD | F6: 10.1109/access.2017.2755858 | G6: Concurrent-transmission multi-hop LoRa (2017, foundational)
A7: 2.1 | B7: R179 | C7: Routing in LoRa for smart cities: A gossip study | D7: 2022 | E7: FLOOD | F7: 10.1016/j.future.2022.05.028 | G7: Gossip routing study for smart cities
A8: 2.1 | B8: R012 | C8: Design Considerations and Performance Evaluation of Gossip Routing in LoRa-Based Linear Networks | D8: 2023 | E8: FLOOD | F8: 10.3390/fi15110366 | G8: Gossip routing in linear LoRa networks; compares with flooding
A9: 2.1 | B9: R128 | C9: Flooding in LoRa Mesh Networks | D9: 2024 | E9: FLOOD | F9: 10.1109/itnac62915.2024.10815298 | G9: Flooding in LoRa mesh networks: why flooding fits LoRa
A10: 2.1 | B10: R053 | C10: LoRa as a Mesh Networking Technology | D10: 2025 | E10: FLOOD | F10: 10.1109/icoin63865.2025.10992870 | G10: LoRa as mesh technology: concurrent transmission and flooding
A11: 2.1 | B11: R089 | C11: A Routing Protocol for LoRA Mesh Networks | D11: 2018 | E11: PROTO | F11: 10.1109/wowmom.2018.8449743 | G11: Early LoRa mesh routing protocol (2018)
A12: 2.1 | B12: R140 | C12: Implementation of a LoRa Mesh Library | D12: 2022 | E12: PROTO | F12: 10.1109/access.2022.3217215 | G12: LoRa mesh library implementation (predecessor of LoRaMesher)
A13: 2.1 | B13: R175 | C13: LoRaute: Routing Messages in Backhaul LoRa Networks for Underserved Regions | D13: 2023 | E13: PROTO | F13: 10.1109/jiot.2023.3281941 | G13: LoRaute: routing in community backhaul LoRa networks
... A45: 2.3 | B45: R253 | C45: Artificial Intelligence in Mitigating Security Threats for Lightweight IoT Devices: A Survey of Technologies, Protocols, and Future Challenges | D45: 2026 | E45: HWSURVEY | F45: 10.1109/jiot.2025.3649316 | G45: Survey: security on <512 kB RAM IoT devices (BLE, Zigbee, LoRa)
